<?xml version="1.0" encoding="utf-8"?><CONS.ACT xmlns:xsi="http://www.w3.org/2001/XMLSchema-instance" xsi:noNamespaceSchemaLocation="http://formex.publications.europa.eu/schema/formex-05.56-20160701.xd"><INFO.CONSLEG CONSLEG.DATE="20181031" CONSLEG.REF="2016R0438" DATE.LAST.MOD="20181030" END="NONE" END.DATE="99999999" LEG.VAL="REG" PROD.SEQ="001.001.0" START.DATE="20200401"/><INFO.PROD PROD.DATE="20181031" PROD.SYSTEM="CONSLEG.NEW" PRODUCER="ES"/><CONS.DOC><BIB.INSTANCE><DOCUMENT.REF FILE="CL2016R0438EN0010010.0001.doc.xml"><LG.OJ>EN</LG.OJ><PAGE.FIRST>1</PAGE.FIRST></DOCUMENT.REF><DATE ISO="20200401">20200401</DATE><LG.DOC>EN</LG.DOC><PAGE.FIRST>1</PAGE.FIRST><PAGE.SEQ>1</PAGE.SEQ><PAGE.LAST>21</PAGE.LAST><PAGE.TOTAL>21</PAGE.TOTAL></BIB.INSTANCE><FAM.COMP LEG.VAL="REG"><BIB.DATA><BIB.INSTANCE.CONS><DOCUMENT.REF.CONS><COLL>L</COLL><NO.OJ>078</NO.OJ><YEAR>2016</YEAR><LG.OJ>EN</LG.OJ><PAGE.FIRST>11</PAGE.FIRST><PAGE.SEQ>1</PAGE.SEQ><VOLUME.REF>01</VOLUME.REF></DOCUMENT.REF.CONS><EEA/><DATE ISO="20160324">20160324</DATE><LG.DOC>EN</LG.DOC><NO.SEQ>0004</NO.SEQ><PAGE.FIRST>11</PAGE.FIRST><PAGE.SEQ>1</PAGE.SEQ><PAGE.LAST>30</PAGE.LAST><PAGE.TOTAL>20</PAGE.TOTAL><NO.DOC FORMAT="YN" TYPE="OJ"><NO.CURRENT>438</NO.CURRENT><YEAR>2016</YEAR><COM>EU</COM></NO.DOC></BIB.INSTANCE.CONS><NO.CELEX>32016R0438</NO.CELEX><DATE ISO="20151217">20151217</DATE><TITLE><TI><P><HT TYPE="UC">Commission Delegated Regulation</HT> (EU) 2016/438</P><P>of <DATE ISO="20151217">17 December 2015</DATE></P><P>supplementing Directive 2009/65/EC of the European Parliament and of the Council with regard to obligations of depositaries</P><P>(Text with EEA relevance)</P></TI></TITLE></BIB.DATA><GR.MOD.ACT><MOD.ACT EXISTS="YES" LEG.VAL="REG" TYPE="MOD"><BIB.DATA><BIB.INSTANCE.CONS><DOCUMENT.REF.CONS><COLL>L</COLL><NO.OJ>271</NO.OJ><YEAR>2018</YEAR><LG.OJ>EN</LG.OJ><PAGE.FIRST>6</PAGE.FIRST><PAGE.SEQ>1</PAGE.SEQ><VOLUME.REF>01</VOLUME.REF></DOCUMENT.REF.CONS><EEA/><DATE ISO="20181030">20181030</DATE><LG.DOC>EN</LG.DOC><NO.SEQ>0002</NO.SEQ><PAGE.FIRST>6</PAGE.FIRST><PAGE.SEQ>1</PAGE.SEQ><PAGE.LAST>9</PAGE.LAST><PAGE.TOTAL>4</PAGE.TOTAL><NO.DOC FORMAT="YN" TYPE="OJ"><NO.CURRENT>1619</NO.CURRENT><YEAR>2018</YEAR><COM>EU</COM></NO.DOC></BIB.INSTANCE.CONS><NO.CELEX>32018R1619</NO.CELEX><DATE ISO="20180712">20180712</DATE><TITLE><TI><P><HT TYPE="UC">Commission Delegated Regulation</HT> (EU) 2018/1619</P><P>of <DATE ISO="20180712">12 July 2018</DATE></P><P>amending Delegated Regulation (EU) 2016/438 as regards safe-keeping duties of depositaries</P><P>(Text with EEA relevance)</P></TI></TITLE></BIB.DATA></MOD.ACT></GR.MOD.ACT></FAM.COMP><?PAGE NO='2'?><TITLE><TI><P><HT TYPE="UC">Commission Delegated Regulation</HT> (EU) 2016/438</P><P>of <DATE ISO="20151217">17 December 2015</DATE></P><P>supplementing Directive 2009/65/EC of the European Parliament and of the Council with regard to obligations of depositaries</P><P>(Text with EEA relevance)</P></TI></TITLE><PREAMBLE><PREAMBLE.INIT></PREAMBLE.INIT><PREAMBLE.FINAL></PREAMBLE.FINAL></PREAMBLE><ENACTING.TERMS><DIVISION><TITLE><TI><P>CHAPTER 1</P></TI><STI><P><HT TYPE="BOLD">DEFINITIONS AND DETAILS OF THE WRITTEN CONTRACT</HT></P><P>(Article 22(2) of Directive 2009/65/EC)</P></STI></TITLE><ARTICLE IDENTIFIER="001"><TI.ART>Article 1</TI.ART><STI.ART>Definitions</STI.ART><ALINEA><P>For the purpose of this Regulation, the following definitions shall apply:</P><LIST TYPE="alpha"><ITEM><NP><NO.P>(a)</NO.P><TXT><QUOT.START CODE="2018" ID="QS0001" REF.END="QE0001"/>link<QUOT.END CODE="2019" ID="QE0001" REF.START="QS0001"/> means a situation in which two and more natural or legal persons are either linked by a direct or indirect holding in an undertaking which represents 10 % or more of the capital or of the voting rights or which makes it possible to exercise a significant influence over the management of the undertaking in which that holding subsists;</TXT></NP></ITEM><ITEM><NP><NO.P>(b)</NO.P><TXT><QUOT.START CODE="2018" ID="QS0002" REF.END="QE0002"/>group link<QUOT.END CODE="2019" ID="QE0002" REF.START="QS0002"/> means a situation in which two or more undertakings or entities belong to the same group within the meaning of Article 2(11) of Directive 2013/34/EU of the European Parliament and of the Council<NOTE NOTE.ID="E0001" NUMBERING="ARAB" TYPE="FOOTNOTE"><P>Directive 2013/34/EU of the European Parliament and of the Council of <DATE ISO="20130626">26 June 2013</DATE> on the annual financial statements, consolidated financial statements and related reports of certain types of undertakings, amending Directive 2006/43/EC of the European Parliament and of the Council and repealing Council Directives 78/660/EEC and 83/349/EEC (<REF.DOC.OJ COLL="L" DATE.PUB="20130629" NO.OJ="182" PAGE.FIRST="19">OJ L 182, 29.6.2013, p. 19</REF.DOC.OJ>).</P></NOTE> or international accounting standards adopted in accordance with Regulation (EC) No 1606/2002 of the European Parliament and of the Council<NOTE NOTE.ID="E0002" NUMBERING="ARAB" TYPE="FOOTNOTE"><P>Regulation (EC) No 1606/2002 of the European Parliament and of the Council of <DATE ISO="20020719">19 July 2002</DATE> on the application of international accounting standards (<REF.DOC.OJ COLL="L" DATE.PUB="20020911" NO.OJ="243" PAGE.FIRST="1">OJ L 243, 11.9.2002, p. 1</REF.DOC.OJ>).</P></NOTE>.</TXT></NP></ITEM></LIST></ALINEA></ARTICLE><ARTICLE IDENTIFIER="002"><TI.ART>Article 2</TI.ART><STI.ART>Contract for the appointment of a depositary</STI.ART><PARAG IDENTIFIER="002.001"><NO.PARAG>1.</NO.PARAG><ALINEA>The contract evidencing the appointment of the depositary in accordance with Article 22(2) of Directive 2009/65/EC shall be drawn up between, on the one hand, the depositary and, on the other hand, the investment company or the management company for each of the common funds that the management company manages.</ALINEA></PARAG><PARAG IDENTIFIER="002.002"><NO.PARAG>2.</NO.PARAG><ALINEA><P>The contract shall include at least the following elements:</P><LIST TYPE="alpha"><ITEM><NP><NO.P>(a)</NO.P><TXT>a description of the services to be provided by the depositary and the procedures to be adopted by the depositary for each type of assets in which the UCITS may invest and which are entrusted to the depositary;</TXT></NP></ITEM><?PAGE NO='3'?><ITEM><NP><NO.P>(b)</NO.P><TXT>a description of the way in which the safekeeping and oversight functions are to be performed depending on the types of assets and the geographical regions in which the UCITS plans to invest, including in respect to the safekeeping duties, country lists and procedures for adding or withdrawing countries from the lists. This shall be consistent with the information provided in the UCITS rules, instruments of incorporation and offering documents regarding the assets in which the UCITS may invest;</TXT></NP></ITEM><ITEM><NP><NO.P>(c)</NO.P><TXT>the period of validity and the conditions for amendment and termination of the contract, including the situations which could lead to the termination of the contract and details regarding the termination procedure and the procedures by which the depositary send all relevant information to its successor;</TXT></NP></ITEM><ITEM><NP><NO.P>(d)</NO.P><TXT>the confidentiality obligations applicable to the parties in accordance with relevant laws and regulations. Those obligations shall not impair the ability of competent authorities to have access to the relevant documents and information;</TXT></NP></ITEM><ITEM><NP><NO.P>(e)</NO.P><TXT>the means and procedures by which the depositary transmits to the management company or the investment company all relevant information that it needs in order to perform its duties, including the exercise of any rights attached to assets, and to allow the management company or the investment company to have a timely and accurate overview of the accounts of the UCITS;</TXT></NP></ITEM><ITEM><NP><NO.P>(f)</NO.P><TXT>the means and procedures by which the management company or the investment company transmits all relevant information or ensures the depositary has access to all the information it needs to fulfil its duties, including the procedures ensuring that the depositary will receive information from other parties appointed by the management company or the investment company;</TXT></NP></ITEM><ITEM><NP><NO.P>(g)</NO.P><TXT>the procedures to be followed when an amendment to the UCITS rules, instruments of incorporation or offering documents is being considered, detailing the situations in which the depositary is to be informed, or where the prior agreement of the depositary is needed to proceed with the amendment;</TXT></NP></ITEM><ITEM><NP><NO.P>(h)</NO.P><TXT>all necessary information that needs to be exchanged between the investment company or the management company, or a third party acting on behalf of the UCITS on the one hand, and the depositary, on the other hand, related to the sale, subscription, redemption, issue, cancellation and re-purchase of units of the UCITS;</TXT></NP></ITEM><ITEM><NP><NO.P>(i)</NO.P><TXT>all necessary information that needs to be exchanged between the investment company or the management company, or a third party acting on behalf of the UCITS and the depositary related to the performance of the depositary's duties;</TXT></NP></ITEM><?PAGE NO='4'?><ITEM><NP><NO.P>(j)</NO.P><TXT>where parties to the contract envisage appointing third parties to carry out parts of their respective duties, a commitment to provide, on a regular basis, details of any third party appointed and, upon request, information on the criteria used to select the third party and the steps envisaged to monitor the activities carried out by the selected third party;</TXT></NP></ITEM><ITEM><NP><NO.P>(k)</NO.P><TXT>information on the tasks and responsibilities of the parties to the contract in respect of obligations relating to the prevention of money laundering and the financing of terrorism;</TXT></NP></ITEM><ITEM><NP><NO.P>(l)</NO.P><TXT>information on all cash accounts opened in the name of the investment company or of the management company acting on behalf of the UCITS and the procedures ensuring that the depositary will be informed when any new account is opened;</TXT></NP></ITEM><ITEM><NP><NO.P>(m)</NO.P><TXT>details regarding the depositary's escalation procedures, including the identification of the persons to be contacted within the management company or the investment company by the depositary when it launches such a procedure;</TXT></NP></ITEM><ITEM><NP><NO.P>(n)</NO.P><TXT>a commitment by the depositary to notify that the segregation of assets is no longer sufficient to ensure protection from insolvency of a third party, to whom safekeeping has been delegated in accordance with Article 22a of Directive 2009/65/EC in a specific jurisdiction;</TXT></NP></ITEM><ITEM><NP><NO.P>(o)</NO.P><TXT>the procedures ensuring that the depositary, in respect of its duties, has the ability to enquire into the conduct of the management company or the investment company and to assess the quality of information received, including by way of having access to the books of the management company or the investment company and by way of on-site visits;</TXT></NP></ITEM><ITEM><NP><NO.P>(p)</NO.P><TXT>the procedures ensuring that the management company or the investment company are enabled to review the performance of the depositary in respect of the depositary's duties.</TXT></NP></ITEM></LIST></ALINEA><ALINEA>The details of the means and procedures set out in points (a) to (p) shall be described in the contract appointing the depositary and any subsequent amendment to the contract.</ALINEA></PARAG><PARAG IDENTIFIER="002.003"><NO.PARAG>3.</NO.PARAG><ALINEA>The parties may agree to transmit all or part of the information that flows between them electronically provided that proper recording of such information is ensured.</ALINEA></PARAG><PARAG IDENTIFIER="002.004"><NO.PARAG>4.</NO.PARAG><ALINEA>Unless otherwise provided by national law, there shall be no obligation to enter into a specific written contract for each common fund.</ALINEA><ALINEA>The management company and the depositary may enter into a single contract agreement listing the common funds managed by that management company to which the contract applies.</ALINEA></PARAG><?PAGE NO='5'?><PARAG IDENTIFIER="002.005"><NO.PARAG>5.</NO.PARAG><ALINEA>The contract evidencing the appointment of the depositary and any subsequent agreement shall indicate the law applicable to the contract.</ALINEA></PARAG></ARTICLE></DIVISION><DIVISION><TITLE><TI><P>CHAPTER 2</P></TI><STI><P><HT TYPE="BOLD">DEPOSITARY FUNCTIONS, DUE DILIGENCE DUTIES, SEGREGATION OBLIGATION AND INSOLVENCY PROTECTION</HT></P><P>(Article 22(3), (4) and (5) and Article 22a(2)(c) and (d) of Directive 2009/65/EC)</P></STI></TITLE><ARTICLE IDENTIFIER="003"><TI.ART>Article 3</TI.ART><STI.ART>Oversight duties — general requirements</STI.ART><PARAG IDENTIFIER="003.001"><NO.PARAG>1.</NO.PARAG><ALINEA>At the time of its appointment, a depositary shall assess the risks associated with the nature, scale and complexity of the investment policy and strategy of the UCITS' and with the organisation of the management company or the investment company. On the basis of that assessment, the depositary shall devise oversight procedures which are appropriate to the UCITS and the assets in which it invests and which are then implemented and applied. Those procedures shall be regularly updated.</ALINEA></PARAG><PARAG IDENTIFIER="003.002"><NO.PARAG>2.</NO.PARAG><ALINEA>In performing its oversight duties under Article 22(3) of Directive 2009/65/EC, a depositary shall perform <HT TYPE="ITALIC">ex post</HT> controls and verifications of processes and procedures that are under the responsibility of the management company or the investment company or an appointed third party. The depositary shall in all circumstances ensure that an appropriate verification and reconciliation procedure exists which is implemented and applied and frequently reviewed. The management company or the investment company shall ensure that all instructions related to the UCITS' assets and operations are sent to the depositary, so that the depositary is able to perform its own verification or reconciliation procedure.</ALINEA></PARAG><PARAG IDENTIFIER="003.003"><NO.PARAG>3.</NO.PARAG><ALINEA>A depositary shall establish a clear and comprehensive escalation procedure to deal with situations where potential discrepancies are detected in the course of its oversight duties, the details of which shall be made available to the competent authorities of the management company or the investment company upon request.</ALINEA></PARAG><PARAG IDENTIFIER="003.004"><NO.PARAG>4.</NO.PARAG><ALINEA>The management company or the investment company shall provide the depositary, upon commencement of its duties and on an ongoing basis thereafter, with all the relevant information it needs in order to comply with its obligations pursuant to Article 22(3) of Directive 2009/65/EC including information to be provided to the depositary by third parties.</ALINEA><ALINEA>The management company or the investment company shall particularly ensure that the depositary is able to have access to the books and perform on-site visits on premises of the management company or the investment company and of any service provider appointed by the management company or the investment company, or to review reports and statements of recognised external certifications by qualified independent auditors or other experts in order to ensure the adequacy and relevance of the procedures in place.</ALINEA></PARAG></ARTICLE><?PAGE NO='6'?><ARTICLE IDENTIFIER="004"><TI.ART>Article 4</TI.ART><STI.ART>Duties regarding subscription and redemptions</STI.ART><PARAG IDENTIFIER="004.001"><NO.PARAG>1.</NO.PARAG><ALINEA><P>A depositary shall be deemed to comply with the requirements set out in point (a) of Article 22(3) of Directive 2009/65/EC where it ensures that the management company or the investment company has established, implements and applies an appropriate and consistent procedure to:</P><LIST TYPE="alpha"><ITEM><NP><NO.P>(a)</NO.P><TXT>reconcile the subscription orders with the subscription proceeds, and the number of units issued with the subscription proceeds received by the UCITS;</TXT></NP></ITEM><ITEM><NP><NO.P>(b)</NO.P><TXT>reconcile the redemption orders with the redemptions paid, and the number of units cancelled with the redemptions paid by the UCITS;</TXT></NP></ITEM><ITEM><NP><NO.P>(c)</NO.P><TXT>verify on a regular basis that the reconciliation procedure is appropriate.</TXT></NP></ITEM></LIST></ALINEA><ALINEA>For the purpose of points (a), (b) and (c), the depositary shall in particular regularly check that there is consistency between the total number of units in the UCITS' accounts and the total number of outstanding units that appear in the UCITS' register.</ALINEA></PARAG><PARAG IDENTIFIER="004.002"><NO.PARAG>2.</NO.PARAG><ALINEA>A depositary shall ensure and regularly check that the procedures regarding the sale, issue, repurchase, redemption and cancellation of units of the UCITS comply with the applicable national law and with the UCITS rules or instruments of incorporation and verify that those procedures are effectively implemented.</ALINEA></PARAG><PARAG IDENTIFIER="004.003"><NO.PARAG>3.</NO.PARAG><ALINEA>The frequency of the depositary's checks shall be consistent with the flow of subscriptions and redemptions.</ALINEA></PARAG></ARTICLE><ARTICLE IDENTIFIER="005"><TI.ART>Article 5</TI.ART><STI.ART>Duties regarding the valuation of units</STI.ART><PARAG IDENTIFIER="005.001"><NO.PARAG>1.</NO.PARAG><ALINEA><P>A depositary shall be deemed to comply with the requirements set out in point (b) of Article 22(3) of Directive 2009/65/EC where it puts in place procedures to:</P><LIST TYPE="alpha"><ITEM><NP><NO.P>(a)</NO.P><TXT>verify on an ongoing basis that appropriate and consistent procedures are established and applied for the valuation of the assets of the UCITS in compliance with the applicable national law as laid down in Article 85 of Directive 2009/65/EC and with the UCITS rules or instruments of incorporation;</TXT></NP></ITEM><ITEM><NP><NO.P>(b)</NO.P><TXT>ensure that the valuation policies and procedures are effectively implemented and periodically reviewed.</TXT></NP></ITEM></LIST></ALINEA></PARAG><PARAG IDENTIFIER="005.002"><NO.PARAG>2.</NO.PARAG><ALINEA>The depositary, shall conduct the verifications referred to in paragraph 1 at a frequency consistent with the frequency of the UCITS' valuation policy as defined in the national law adopted in accordance with Article 85 of Directive 2009/65/EC, and with the UCITS rules or instruments of incorporation.</ALINEA></PARAG><PARAG IDENTIFIER="005.003"><NO.PARAG>3.</NO.PARAG><ALINEA>Where a depositary considers that the calculation of the value of the units of the UCITS has not been performed in compliance with applicable law or the UCITS rules or with instruments of incorporation, it shall notify the management company or the investment company and ensure that timely remedial action is taken in the best interest of the investors in the UCITS.</ALINEA></PARAG></ARTICLE><?PAGE NO='7'?><ARTICLE IDENTIFIER="006"><TI.ART>Article 6</TI.ART><STI.ART>Duties regarding the carrying out of the UCITS' instructions</STI.ART><ALINEA><P>A depositary shall be deemed to comply with the requirements set out in point (c) of Article 22(3) of Directive 2009/65/EC where it establishes and implements at least:</P><LIST TYPE="alpha"><ITEM><NP><NO.P>(a)</NO.P><TXT>appropriate procedures to verify that instructions of the management company or the investment company comply with applicable laws and regulations and with the UCITS' rules and instruments of incorporation;</TXT></NP></ITEM><ITEM><NP><NO.P>(b)</NO.P><TXT>an escalation procedure where the UCITS has breached one of the limits or restrictions referred to in second subparagraph.</TXT></NP></ITEM></LIST></ALINEA><ALINEA>For the purposes of point (a), the depositary shall in particular monitor the UCITS' compliance with investment restrictions and leverage limits to which the UCITS is subject. The procedures referred to in point (a) shall be proportionate to the nature, scale and complexity of the UCITS.</ALINEA></ARTICLE><ARTICLE IDENTIFIER="007"><TI.ART>Article 7</TI.ART><STI.ART>Duties regarding the timely settlement of transactions</STI.ART><PARAG IDENTIFIER="007.001"><NO.PARAG>1.</NO.PARAG><ALINEA>A depositary shall be deemed to comply with the requirements set out in point (d) of Article 22(3) of Directive 2009/65/EC where it establishes a procedure to detect any situation where consideration in transactions involving the assets of the UCITS is not remitted to the UCITS within the usual time limits, to notify the management company or the investment company accordingly and, where the situation has not been remedied, to request the restitution of the assets from the counterparty where possible.</ALINEA></PARAG><PARAG IDENTIFIER="007.002"><NO.PARAG>2.</NO.PARAG><ALINEA>Where transactions do not take place on a regulated market, the depositary shall carry out its duties pursuant to paragraph 1 taking into account the conditions attached to these transactions.</ALINEA></PARAG></ARTICLE><ARTICLE IDENTIFIER="008"><TI.ART>Article 8</TI.ART><STI.ART>Duties related to the UCITS' income calculation and distribution</STI.ART><PARAG IDENTIFIER="008.001"><NO.PARAG>1.</NO.PARAG><ALINEA><P>A depositary shall be deemed to comply with the requirements set out in point (e) of Article 22(3) of Directive 2009/65/EC where it:</P><LIST TYPE="alpha"><ITEM><NP><NO.P>(a)</NO.P><TXT>ensures that the net income calculation is applied in accordance with the UCITS rules, instruments of incorporation and applicable national law every time income is to be distributed;</TXT></NP></ITEM><ITEM><NP><NO.P>(b)</NO.P><TXT>ensures that appropriate measures are taken where the UCITS' auditors have expressed reserves on the annual financial statements. The management company or the investment company shall provide the depositary with all information on reserves expressed on the financial statements;</TXT></NP></ITEM><ITEM><NP><NO.P>(c)</NO.P><TXT>checks the completeness and accuracy of dividend payments, every time income is to be distributed.</TXT></NP></ITEM></LIST></ALINEA></PARAG><?PAGE NO='8'?><PARAG IDENTIFIER="008.002"><NO.PARAG>2.</NO.PARAG><ALINEA>Where a depositary considers that the income calculation has not been applied in compliance with applicable law or with the UCITS rules or instruments of incorporation, it shall notify the management company or the investment company and ensure that timely remedial action has been taken in the best interest of the UCITS' investors.</ALINEA></PARAG></ARTICLE><ARTICLE IDENTIFIER="009"><TI.ART>Article 9</TI.ART><STI.ART>Cash monitoring — general requirements</STI.ART><PARAG IDENTIFIER="009.001"><NO.PARAG>1.</NO.PARAG><ALINEA>Where a cash account is maintained or opened at an entity referred to in point (b) of Article 22(4) of Directive 2009/65/EC in the name of the investment company or of the management company acting on behalf of the UCITS, the management company or the investment company shall ensure that the depositary is provided, upon commencement of its duties and on an ongoing basis, with all relevant information necessary for having a clear overview of all UCITS' cash flows so that the depositary is able to comply with its obligations.</ALINEA></PARAG><PARAG IDENTIFIER="009.002"><NO.PARAG>2.</NO.PARAG><ALINEA>Upon the depositary's appointment the investment company or the management company shall inform the depositary of all existing cash accounts opened in the name of the investment company, or the management company acting on behalf of the UCITS.</ALINEA></PARAG><PARAG IDENTIFIER="009.003"><NO.PARAG>3.</NO.PARAG><ALINEA>The investment company or the management company shall ensure that the depositary is provided with all information related to the opening of any new cash account by the investment company, or the management company acting on behalf of the UCITS.</ALINEA></PARAG></ARTICLE><ARTICLE IDENTIFIER="010"><TI.ART>Article 10</TI.ART><STI.ART>Monitoring of the UCITS' cash flows</STI.ART><PARAG IDENTIFIER="010.001"><NO.PARAG>1.</NO.PARAG><ALINEA><P>A depositary shall be deemed to comply with the requirements set out in Article 22(4) of Directive 2009/65/EC where it ensures effective and proper monitoring of the UCITS' cash flows and, in particular, it at least:</P><LIST TYPE="alpha"><ITEM><NP><NO.P>(a)</NO.P><TXT>ensures that all cash of the UCITS is booked in accounts opened with either a central bank or a credit institution authorised in accordance with Directive 2013/36/EU of the European Parliament and of the Council<NOTE NOTE.ID="E0003" NUMBERING="ARAB" TYPE="FOOTNOTE"><P>Directive 2013/36/EU of the European Parliament and of the Council of <DATE ISO="20130626">26 June 2013</DATE> on access to the activity of credit institutions and the prudential supervision of credit institutions and investment firms, amending Directive 2002/87/EC and repealing Directives 2006/48/EC and 2006/49/EC (<REF.DOC.OJ COLL="L" DATE.PUB="20130627" NO.OJ="176" PAGE.FIRST="338">OJ L 176, 27.6.2013, p. 338</REF.DOC.OJ>).</P></NOTE> or a credit institution authorised in a third country, where cash accounts are required for the purposes of the UCITS' operations, provided that the prudential supervisory and regulatory requirements applied to credit institutions in that third country are considered by the competent authority of the UCITS home Member State as at least equivalent to those applied in the Union;</TXT></NP></ITEM><?PAGE NO='9'?><ITEM><NP><NO.P>(b)</NO.P><TXT>implements effective and proper procedures to reconcile all cash flow movements and performs such reconciliations on a daily basis, or, in case of infrequent cash movements, when such cash flow movements occur;</TXT></NP></ITEM><ITEM><NP><NO.P>(c)</NO.P><TXT>implements appropriate procedures to identify at the close of each business day significant cash flows and cash flows which could be inconsistent with UCITS' operations;</TXT></NP></ITEM><ITEM><NP><NO.P>(d)</NO.P><TXT>reviews periodically the adequacy of those procedures, including through a full review of the reconciliation process at least once a year, and ensures that the cash accounts opened in the name of the investment company or in the name of the management company acting on behalf of the UCITS or in the name of the depositary acting on behalf of the UCITS are included in the reconciliation process;</TXT></NP></ITEM><ITEM><NP><NO.P>(e)</NO.P><TXT>monitors on an ongoing basis the outcomes of the reconciliations and the actions taken as a result of any discrepancies identified by the reconciliation procedures, and notifies the management company or the investment company if a discrepancy has not been corrected without undue delay and also the competent authorities if the situation cannot be corrected;</TXT></NP></ITEM><ITEM><NP><NO.P>(f)</NO.P><TXT>checks that there is consistency between its own records of cash positions and those of the UCITS.</TXT></NP></ITEM></LIST></ALINEA><ALINEA>For the purposes of assessing the equivalence of prudential supervisory and regulatory requirements applied to credit institutions of a third country referred to in point (a), competent authorities shall take into account the implementing acts adopted by the Commission pursuant to Article 107(4) of Regulation (EU) No 575/2013 of the European Parliament and of the Council<NOTE NOTE.ID="E0004" NUMBERING="ARAB" TYPE="FOOTNOTE"><P>Regulation (EU) No 575/2013 of the European Parliament and of the Council of <DATE ISO="20130626">26 June 2013</DATE> on prudential requirements for credit institutions and investment firms and amending Regulation (EU) No 648/2012 (<REF.DOC.OJ COLL="L" DATE.PUB="20130627" NO.OJ="176" PAGE.FIRST="1">OJ L 176, 27.6.2013, p. 1</REF.DOC.OJ>).</P></NOTE>.</ALINEA></PARAG><PARAG IDENTIFIER="010.002"><NO.PARAG>2.</NO.PARAG><ALINEA>The management company or the investment company shall ensure that all instructions and information related to a cash account opened with a third party are sent to the depositary, to enable the depositary to perform its own reconciliation procedure.</ALINEA></PARAG></ARTICLE><ARTICLE IDENTIFIER="011"><TI.ART>Article 11</TI.ART><STI.ART>Duties regarding payments upon the subscriptions</STI.ART><ALINEA>A management company or an investment company shall ensure that the depositary is provided with information about payments made by or on behalf of investors upon the subscription of units of an UCITS at the close of each business day on which the investment company or the management company acting on behalf of the UCITS, or a party acting on behalf of UCITS, such as a transfer agent, receives such payments or an order from the investor. The management company or the investment<?PAGE NO='10'?> company shall ensure that the depositary receives all other relevant information it needs to make sure that the payments are booked in cash accounts opened in the name of the investment company or in the name of the management company acting on behalf of the UCITS or in the name of the depositary in accordance with Article 22(4) of Directive 2009/65/EC.</ALINEA></ARTICLE><ARTICLE IDENTIFIER="012"><TI.ART>Article 12</TI.ART><STI.ART>Financial instruments to be held in custody</STI.ART><PARAG IDENTIFIER="012.001"><NO.PARAG>1.</NO.PARAG><ALINEA><P>Financial instruments belonging to the UCITS which are not able to be physically delivered to the depositary shall be included in the scope of the custody duties of the depositary where all of the following requirements are met:</P><LIST TYPE="alpha"><ITEM><NP><NO.P>(a)</NO.P><TXT>they are financial instruments referred to in points (a) to (e) and (h) of Article 50(1) of Directive 2009/65/EC or transferable securities which embed derivatives as referred to in the fourth subparagraph of Article 51(3) of Directive 2009/65/EC;</TXT></NP></ITEM><ITEM><NP><NO.P>(b)</NO.P><TXT>they are capable of being registered or held in a securities account directly or indirectly in the name of the depositary.</TXT></NP></ITEM></LIST></ALINEA></PARAG><PARAG IDENTIFIER="012.002"><NO.PARAG>2.</NO.PARAG><ALINEA>Financial instruments which, in accordance with applicable national law, are only directly registered in the name of the UCITS with the issuer itself or its agent, such as a registrar or a transfer agent, shall not be held in custody.</ALINEA></PARAG><PARAG IDENTIFIER="012.003"><NO.PARAG>3.</NO.PARAG><ALINEA>Financial instruments belonging to the UCITS which are able to be physically delivered to the depositary shall in all cases be included in the scope of the custody duties of the depositary.</ALINEA></PARAG></ARTICLE><ARTICLE IDENTIFIER="013"><TI.ART>Article 13</TI.ART><STI.ART>Safekeeping duties with regard to assets held in custody</STI.ART><PARAG IDENTIFIER="013.001"><NO.PARAG>1.</NO.PARAG><ALINEA><P>A depositary shall be deemed to comply with the requirements set out in point (a) of Article 22(5) of Directive 2009/65/EC with respect to financial instruments to be held in custody where it ensures that:</P><LIST TYPE="alpha"><ITEM><NP><NO.P>(a)</NO.P><TXT>the financial instruments are properly registered in accordance with Article 22(5)(a)(ii) of Directive 2009/65/EC;</TXT></NP></ITEM><ITEM><NP><NO.P>(b)</NO.P><TXT>records and segregated accounts are maintained in a way that ensures their accuracy, and in particular record the correspondence with the financial instruments and cash held for UCITS;</TXT></NP></ITEM><?CLG.MDFO ID="O001001M001000" IDREF="C001001M001000" ACTION="REPLACED" LEVEL="STRUCTURE" COMMAND="EXPLICIT" ACTIVE.DOC="32018R1619" ACTIVE.LOC="AR:1;PT:1;PT:a;PT:i" MOD.LEVEL="1"?><ITEM><NP><NO.P>(c)</NO.P><TXT>reconciliations are conducted as frequently as necessary between the depositary's internal accounts and records and those of any third party to whom safekeeping has been delegated in accordance with Article 22a of Directive 2009/65/EC;</TXT></NP></ITEM><?CLG.MDFC ID="C001001M001000" IDREF="O001001M001000"?><ITEM><NP><NO.P>(d)</NO.P><TXT>due care is exercised in relation to the financial instruments held in custody in order to ensure a high standard of investor protection;</TXT></NP></ITEM><?PAGE NO='11'?><ITEM><NP><NO.P>(e)</NO.P><TXT>all relevant custody risks throughout the custody chain are assessed and monitored and the management company or the investment company is informed of any material risk identified;</TXT></NP></ITEM><ITEM><NP><NO.P>(f)</NO.P><TXT>adequate organisational arrangements are introduced to minimise the risk of loss or diminution of the financial instruments, or of rights in connection with those financial instruments as a result of fraud, poor administration, inadequate registering or negligence;</TXT></NP></ITEM><ITEM><NP><NO.P>(g)</NO.P><TXT>the UCITS's ownership right or the ownership right of the management company acting on behalf of the UCITS over the assets is verified.</TXT></NP></ITEM></LIST></ALINEA><?CLG.MDFO ID="O001001M002000" IDREF="C001001M002000" ACTION="INSERTED" LEVEL="STRUCTURE" COMMAND="EXPLICIT" ACTIVE.DOC="32018R1619" ACTIVE.LOC="AR:1;PT:1;PT:a;PT:ii" MOD.LEVEL="1"?><ALINEA><P>In relation to point (c) of the first subparagraph, the frequency of the reconciliations shall be determined on the basis of the following:</P><LIST TYPE="alpha"><ITEM><NP><NO.P>(a)</NO.P><TXT>the normal trading activity of the UCITS;</TXT></NP></ITEM><ITEM><NP><NO.P>(b)</NO.P><TXT>any trade occurring outside the normal trading activity;</TXT></NP></ITEM><ITEM><NP><NO.P>(c)</NO.P><TXT>any trade occurring on behalf of any other client whose assets are held by the third party in the same financial instruments account as the assets of the UCITS.</TXT></NP></ITEM></LIST></ALINEA><?CLG.MDFC ID="C001001M002000" IDREF="O001001M002000"?></PARAG><?CLG.MDFO ID="O001001M003000" IDREF="C001001M003000" ACTION="REPLACED" LEVEL="STRUCTURE" COMMAND="EXPLICIT" ACTIVE.DOC="32018R1619" ACTIVE.LOC="AR:1;PT:1;PT:b" MOD.LEVEL="1"?><PARAG IDENTIFIER="013.002"><NO.PARAG>2.</NO.PARAG><ALINEA>Where a depositary has delegated its safekeeping functions, with regard to assets held in custody, to a third party in accordance with Article 22a of Directive 2009/65/EC, it shall remain subject to the requirements of points (a) to (e) of paragraph 1. The depositary shall also ensure that the third party complies with the requirements of points (b) to (g) of paragraph 1.</ALINEA></PARAG><?CLG.MDFC ID="C001001M003000" IDREF="O001001M003000"?></ARTICLE><ARTICLE IDENTIFIER="014"><TI.ART>Article 14</TI.ART><STI.ART>Safekeeping duties regarding ownership verification and record keeping</STI.ART><PARAG IDENTIFIER="014.001"><NO.PARAG>1.</NO.PARAG><ALINEA>The management company or the investment company shall provide the depositary, upon commencement of its duties and on an ongoing basis thereafter, with all relevant information it needs to comply with its obligations pursuant to point (b) of Article 22(5) of Directive 2009/65/EC, and ensure that the depositary is provided with all relevant information by third parties.</ALINEA></PARAG><PARAG IDENTIFIER="014.002"><NO.PARAG>2.</NO.PARAG><ALINEA><P>A depositary shall be deemed to comply with the requirements set out in point (b) of Article 22(5) of Directive 2009/65/EC where it at least:</P><LIST TYPE="alpha"><ITEM><NP><NO.P>(a)</NO.P><TXT>has access without undue delay to all relevant information it needs in order to perform its ownership verification and record-keeping duties, including relevant information to be provided to the depositary by third parties;</TXT></NP></ITEM><ITEM><NP><NO.P>(b)</NO.P><TXT>possesses sufficient and reliable information for it to be satisfied of the UCITS' ownership right over the assets;</TXT></NP></ITEM><ITEM><NP><NO.P>(c)</NO.P><TXT>maintains a record of those assets for which it is satisfied that the UCITS holds the ownership by:</TXT><?PAGE NO='12'?><P><LIST TYPE="roman"><ITEM><NP><NO.P>(i)</NO.P><TXT>registers in its records, in the name of the UCITS, assets, including their respective notional amounts, for which it is satisfied that the UCITS holds the ownership;</TXT></NP></ITEM><ITEM><NP><NO.P>(ii)</NO.P><TXT>is able to provide at any time a comprehensive and up-to-date inventory of the UCITS' assets, including their respective notional amounts.</TXT></NP></ITEM></LIST></P></NP></ITEM></LIST></ALINEA><ALINEA>For the purposes of point (c)(ii) of this paragraph, the depositary shall ensure it has procedures in place so that registered assets cannot be assigned, transferred, exchanged or delivered without the depositary or the third party to whom the safekeeping has been delegated in accordance with Article 22a of Directive 2009/65/EC having been informed of such transactions. The depositary shall have access without undue delay to documentary evidence of each transaction and position from the relevant third party. The management company or the investment company shall ensure that the relevant third party provides the depositary without undue delay with certificates or other documentary evidence every time there is a sale or acquisition of assets or a corporate action resulting in the issue of financial instruments and at least once a year.</ALINEA></PARAG><PARAG IDENTIFIER="014.003"><NO.PARAG>3.</NO.PARAG><ALINEA>A depositary shall ensure that the management company or the investment company has and implements appropriate procedures to verify that the assets acquired by the UCITS are appropriately registered in the name of the UCITS, and shall check the consistency between the positions in the UCITS records and the assets for which the depositary is satisfied that the UCITS holds ownership. The management company or the investment company shall ensure that all instructions and relevant information related to the UCITS' assets are sent to the depositary to enable the depositary to perform its own verification or reconciliation procedure.</ALINEA></PARAG><PARAG IDENTIFIER="014.004"><NO.PARAG>4.</NO.PARAG><ALINEA>A depositary shall set up and implement an escalation procedure for situations where a discrepancy is detected including notification of the management company or the investment company and of the competent authorities if the situation cannot be corrected.</ALINEA></PARAG></ARTICLE><ARTICLE IDENTIFIER="015"><TI.ART>Article 15</TI.ART><STI.ART>Due diligence</STI.ART><PARAG IDENTIFIER="015.001"><NO.PARAG>1.</NO.PARAG><ALINEA>A depositary shall be deemed to comply with the requirements set out in point (c) of Article 22a(2) of Directive 2009/65/EC where it implements and applies an appropriate documented due diligence procedure for the selection and ongoing monitoring of the third party, to whom safekeeping functions are to be or have been delegated in accordance with Article 22a of that Directive. That procedure shall be reviewed regularly and, at least, once a year.</ALINEA></PARAG><PARAG IDENTIFIER="015.002"><NO.PARAG>2.</NO.PARAG><ALINEA><P>When selecting and appointing a third party to whom safekeeping functions are to be delegated in accordance with Article 22a of Directive 2009/65/EC, a depositary shall exercise all due skill, care and diligence to ensure that entrusting financial instruments to that third party provides an adequate standard of protection. The depositary shall at least:</P><?PAGE NO='13'?><LIST TYPE="alpha"><ITEM><NP><NO.P>(a)</NO.P><TXT>assess the regulatory and legal framework, including country risk, custody risk and the enforceability of the contract entered into with that third party. That assessment shall in particular enable the depositary to determine the implications of a potential insolvency of the third party for the assets and rights of the UCITS;</TXT></NP></ITEM><ITEM><NP><NO.P>(b)</NO.P><TXT>ensure that the assessment of the enforceability of the contractual provisions referred to in point (a), where the third party is located in a third country, is based on the legal advice of a natural or legal person independent from the depositary or that third party;</TXT></NP></ITEM><ITEM><NP><NO.P>(c)</NO.P><TXT>assess whether the third party's practice, procedures and internal controls are adequate to ensure that the assets of the UCITS are subject to a high standard of care and protection;</TXT></NP></ITEM><ITEM><NP><NO.P>(d)</NO.P><TXT>assess whether the third party's financial strength and reputation are consistent with the tasks delegated. That assessment shall be based on information provided by the potential third party as well as other data and information;</TXT></NP></ITEM><ITEM><NP><NO.P>(e)</NO.P><TXT>ensure that the third party has the operational and technological capabilities to perform the delegated safekeeping tasks with a high degree of protection and security.</TXT></NP></ITEM></LIST></ALINEA></PARAG><?CLG.MDFO ID="O001001M004000" IDREF="C001001M004000" ACTION="INSERTED" LEVEL="STRUCTURE" COMMAND="EXPLICIT" ACTIVE.DOC="32018R1619" ACTIVE.LOC="AR:1;PT:2" MOD.LEVEL="1"?><PARAG IDENTIFIER="015.002A"><NO.PARAG>2a.</NO.PARAG><ALINEA><P>A contract by which the depositary appoints a third party to hold assets of that depositary's UCITS clients in custody, shall contain at least the following provisions:</P><LIST TYPE="alpha"><ITEM><NP><NO.P>(a)</NO.P><TXT>a guarantee of the depositary's right to information, inspection, and access to the relevant records and financial instruments accounts of the third party holding assets in custody to enable the depositary to fulfil its oversight and due diligence obligations and in particular allow the depositary to:</TXT><P><LIST TYPE="roman"><ITEM><NP><NO.P>(i)</NO.P><TXT>identify all entities within the custody chain;</TXT></NP></ITEM><ITEM><NP><NO.P>(ii)</NO.P><TXT>verify that the quantity of the identified financial instruments recorded in the financial instruments accounts opened in the depositary's books in the name of the UCITS or in the name of the management company acting on behalf of the UCITS matches the quantity of the identified financial instruments held in custody by the third party for that UCITS as recorded in the financial instruments account opened in the third party's books;</TXT></NP></ITEM><ITEM><NP><NO.P>(iii)</NO.P><TXT>verify that the quantity of the identified financial instruments, which are registered and held in a financial instruments account opened at the issuer's Central Securities Depository (<QUOT.START CODE="2018" ID="QS0003" REF.END="QE0003"/>CSD<QUOT.END CODE="2019" ID="QE0003" REF.START="QS0003"/>) or its agent, in the name of the third party on behalf of its clients, matches the quantity of the identified financial instruments recorded in the financial instruments accounts opened in the depositary's books in the name of each of its UCITS clients or in the name of the management company acting on behalf of the UCITS;</TXT></NP></ITEM></LIST></P></NP></ITEM><?PAGE NO='14'?><ITEM><NP><NO.P>(b)</NO.P><TXT>details of equivalent rights and obligations agreed between the third party and another third party, in the event of a further delegation of custody functions.</TXT></NP></ITEM></LIST></ALINEA></PARAG><?CLG.MDFC ID="C001001M004000" IDREF="O001001M004000"?><PARAG IDENTIFIER="015.003"><NO.PARAG>3.</NO.PARAG><ALINEA><P>A depositary shall exercise all due skill, care and diligence in the periodic review and ongoing monitoring to ensure that the third party continues to comply with the criteria provided for in paragraph 2 and the conditions set out in points (a) to (e) of paragraph 3 of Article 22a of Directive 2009/65/EC, and shall at least:</P><LIST TYPE="alpha"><ITEM><NP><NO.P>(a)</NO.P><TXT>monitor the third party's performance and its compliance with the depositary's standards;</TXT></NP></ITEM><ITEM><NP><NO.P>(b)</NO.P><TXT>ensure that the third party exercises a high standard of care, prudence and diligence in the performance of its safekeeping tasks and in particular that it effectively segregates the financial instruments in line with the requirements of Article 16 of this Regulation;</TXT></NP></ITEM><ITEM><NP><NO.P>(c)</NO.P><TXT>review the custody risks associated with the decision to entrust the assets to the third party and without undue delay notify the management company, or the investment company of any change in those risks. That assessment shall be based on information provided by the third party and other data and information. During market turmoil or when a risk has been identified, the frequency and the scope of the review shall be increased;</TXT></NP></ITEM><ITEM><NP><NO.P>(d)</NO.P><TXT>monitor compliance with the prohibition laid down in paragraph 7 of Article 22 of Directive 2009/65/EC;</TXT></NP></ITEM><ITEM><NP><NO.P>(e)</NO.P><TXT>monitor compliance with the prohibition laid down in Article 25 of the Directive 2009/65/EC and the requirements laid down in Articles 21 to 24 of this Regulation.</TXT></NP></ITEM></LIST></ALINEA></PARAG><PARAG IDENTIFIER="015.004"><NO.PARAG>4.</NO.PARAG><ALINEA>Paragraphs 1, 2 and 3 shall apply <HT TYPE="ITALIC">mutatis mutandis</HT> when the third party to whom safekeeping functions are delegated in accordance with Article 22a of Directive 2009/65/EC has decided to sub-delegate all or part its safekeeping functions to another third party pursuant to the third subparagraph of Article 22a(3) of Directive 2009/65/EC.</ALINEA></PARAG><PARAG IDENTIFIER="015.005"><NO.PARAG>5.</NO.PARAG><ALINEA>A depositary shall devise contingency plans for each market in which it appoints a third party to whom safekeeping functions are delegated in accordance with Article 22a of Directive 2009/65/EC. A contingency plan shall include the identification of an alternative provider, if any.</ALINEA></PARAG><PARAG IDENTIFIER="015.006"><NO.PARAG>6.</NO.PARAG><ALINEA>A depositary shall take measures, including termination of the contract, which are in the best interest of the UCITS and its investors where the third party to whom safekeeping has been delegated in accordance with Article 22a of Directive 2009/65/EC no longer complies with the requirements of this Regulation.</ALINEA></PARAG><PARAG IDENTIFIER="015.007"><NO.PARAG>7.</NO.PARAG><ALINEA>Where the depositary has delegated its safekeeping functions in accordance with Article 22a of Directive 2009/65/EC to a third party located in a third country, it shall ensure that the agreement with the third party allows for an early termination, taking into account the need to act in the best interest of UCITS and its investors, in case the applicable insolvency laws and case law no longer recognises the segregation of the UCITS's assets in the event of insolvency or the third party or the conditions laid down in law and case law are no longer fulfilled.</ALINEA></PARAG><?PAGE NO='15'?><PARAG IDENTIFIER="015.008"><NO.PARAG>8.</NO.PARAG><ALINEA>Where the applicable insolvency law and case law no longer recognise the segregation of the UCITS' assets in the event of insolvency of the third party to whom safekeeping functions have been delegated in accordance with Article 22a of Directive 2009/65/EC or no longer ensure that the assets of the depositary's UCITS clients do not form part of the third party's estate in case of insolvency and are unavailable for distribution among, or realisation for the benefit of, creditors of the third party to whom safekeeping functions are delegated pursuant to Article 22a of Directive 2009/65/EC, the depositary shall immediately inform the management company or the investment company.</ALINEA></PARAG><PARAG IDENTIFIER="015.009"><NO.PARAG>9.</NO.PARAG><ALINEA>On receipt of the information referred to under paragraph 8, the management company or the investment company shall immediately notify its competent authority of such information and consider all the appropriate measures in relation to the relevant assets of the UCITS, including their disposal taking into account the need to act in the best interest of the UCITS and its investors.</ALINEA></PARAG></ARTICLE><ARTICLE IDENTIFIER="016"><TI.ART>Article 16</TI.ART><STI.ART>Segregation obligation</STI.ART><?CLG.MDFO ID="O001001M005000" IDREF="C001001M005000" ACTION="REPLACED" LEVEL="STRUCTURE" COMMAND="EXPLICIT" ACTIVE.DOC="32018R1619" ACTIVE.LOC="AR:1;PT:3" MOD.LEVEL="1"?><PARAG IDENTIFIER="016.001"><NO.PARAG>1.</NO.PARAG><ALINEA><P>Where safekeeping functions have been delegated wholly or partly to a third party, a depositary shall ensure that the third party to whom safekeeping functions are delegated pursuant to Article 22a of Directive 2009/65/EC acts in accordance with the segregation obligation laid down in point (c) of Article 22a(3) of that Directive by ensuring and verifying that the third party:</P><LIST TYPE="alpha"><ITEM><NP><NO.P>(a)</NO.P><TXT>correctly records all identified financial instruments in the financial instruments account, which is opened in the third party's books, in order to hold in custody the financial instruments for the depositary's clients, which excludes proprietary financial instruments of the depositary and of the third party and of the third party's other clients, to enable the depositary to match the quantity of the identified financial instruments recorded in the accounts opened in the depositary's books in the name of each of its UCITS clients or in the name of the management company acting on behalf of the UCITS;</TXT></NP></ITEM><ITEM><NP><NO.P>(b)</NO.P><TXT>keeps all necessary records and financial instruments accounts to enable the depositary at any time and without delay to distinguish assets of the depositary's clients from the third party own assets, assets of the third party's other clients and assets held for the depositary for its own account;</TXT></NP></ITEM><ITEM><NP><NO.P>(c)</NO.P><TXT>maintains records and financial securities accounts in a way that ensures their accuracy, and in particular their correspondence to the assets kept safe for the depositary's UCITS clients and on the basis of which the depositary can at any time establish the precise nature, location and ownership status of those assets;</TXT></NP></ITEM><ITEM><NP><NO.P>(d)</NO.P><TXT>provides the depositary with a statement, on a regular basis and whenever a change in circumstances occurs, detailing the assets of the depositary's UCITS clients;</TXT></NP></ITEM><?PAGE NO='16'?><ITEM><NP><NO.P>(e)</NO.P><TXT>conducts reconciliations, as often as necessary, between its financial instruments accounts and internal records and those of the third party to whom it has delegated custody functions in accordance with point (c) of Article 22a(3) of Directive 2009/65/EC.</TXT><P>The frequency of the reconciliation shall be determined in accordance with Article 13(1);</P></NP></ITEM><ITEM><NP><NO.P>(f)</NO.P><TXT>introduces adequate organisational arrangements to minimise the risk of loss or diminution of financial instruments or of rights in connection with those financial instruments as a result of misuse of the financial instruments, fraud, poor administration, inadequate record-keeping or negligence;</TXT></NP></ITEM><ITEM><NP><NO.P>(g)</NO.P><TXT>holds the UCITS' cash in an account or accounts with a central bank of a third country or a credit institution authorised in a third country, provided that the prudential, supervisory and regulatory requirements applied to credit institutions in that third country are considered by the competent authorities of the UCITS home Member States as at least equivalent to those applied in the Union, in accordance with point (c) of Article 22(4) of Directive 2009/65/EC.</TXT></NP></ITEM></LIST></ALINEA></PARAG><?CLG.MDFC ID="C001001M005000" IDREF="O001001M005000"?><PARAG IDENTIFIER="016.002"><NO.PARAG>2.</NO.PARAG><ALINEA>Paragraph 1 shall apply <HT TYPE="ITALIC">mutatis mutandis</HT> when the third party, to whom safekeeping functions are delegated in accordance with Article 22a of Directive 2009/65/EC, has decided to sub-delegate all or part of its safekeeping functions to another third party pursuant to the third subparagraph of Article 22a(3) of Directive 2009/65/EC.</ALINEA></PARAG></ARTICLE><ARTICLE IDENTIFIER="017"><TI.ART>Article 17</TI.ART><STI.ART>Insolvency protection of UCITS assets when delegating custody functions</STI.ART><PARAG IDENTIFIER="017.001"><NO.PARAG>1.</NO.PARAG><ALINEA>A depositary shall ensure that a third party located in a third country, to whom custody functions are to be or have been delegated in accordance with Article 22a of Directive 2009/65/EC takes all necessary steps in order to ensure that in the event of an insolvency of the third party, assets of a UCITS held by the third party in custody are unavailable for distribution among, or realisation for the benefit of, creditors of that third party.</ALINEA></PARAG><PARAG IDENTIFIER="017.002"><NO.PARAG>2.</NO.PARAG><ALINEA><P>A depository shall ensure that the third party takes the following steps:</P><LIST TYPE="alpha"><ITEM><NP><NO.P>(a)</NO.P><TXT><?CLG.MDFO ID="O001001M006000" IDREF="C001001M006000" ACTION="REPLACED" LEVEL="TEXT" COMMAND="EXPLICIT" ACTIVE.DOC="32018R1619" ACTIVE.LOC="AR:1;PT:4;PT:a" MOD.LEVEL="1"?>receives legal advice from an independent natural or legal person confirming that the applicable insolvency law recognises the segregation of the assets of the depositary's clients from the third party's own assets, from the assets of the third party's other clients and from the assets held by the third party for the depositary's own account and that the assets of the depositary's UCITS clients do not form part of the third party's estate in case of insolvency and are unavailable for distribution among, or realisation for the benefit of, creditors of the third party to whom safekeeping functions have been delegated in accordance with Article 22a of Directive 2009/65/EC;<?CLG.MDFC ID="C001001M006000" IDREF="O001001M006000"?></TXT></NP></ITEM><?PAGE NO='17'?><ITEM><NP><NO.P>(b)</NO.P><TXT>ensures that the conditions laid down in the applicable insolvency laws and case law of that third country recognise that the assets of the depositary's UCITS clients are segregated and unavailable for distribution among, or realisation for the benefit of creditors, as referred to in point (a), are met when concluding the delegation agreement with the depositary as well as on an ongoing basis for the entire duration of the delegation;</TXT></NP></ITEM><ITEM><NP><NO.P>(c)</NO.P><TXT>immediately informs the depositary where any of the conditions referred to in point (b) is no longer met;</TXT></NP></ITEM><?CLG.MDFO ID="O001001M007000" IDREF="C001001M007000" ACTION="DELETED" LEVEL="STRUCTURE" COMMAND="EXPLICIT" ACTIVE.DOC="32018R1619" ACTIVE.LOC="AR:1;PT:4;PT:b" MOD.LEVEL="1"?><ITEM><NP><NO.P>(d)</NO.P><TXT>maintains accurate and up-to-date records and accounts of the UCITS' assets on the basis of which the depositary can at any time establish the precise nature, location and ownership status of those assets;</TXT></NP></ITEM><ITEM><NP><NO.P>(e)</NO.P><TXT>provides a statement to the depositary, on a regular basis, and in any case whenever a change occurs, detailing the assets of the depositary's UCITS clients;</TXT></NP></ITEM><?CLG.MDFC ID="C001001M007000" IDREF="O001001M007000"?><ITEM><NP><NO.P>(f)</NO.P><TXT>informs the depositary about the changes of applicable insolvency law and of its effective application.</TXT></NP></ITEM></LIST></ALINEA></PARAG><?CLG.MDFO ID="O001001M008000" IDREF="C001001M008000" ACTION="DELETED" LEVEL="STRUCTURE" COMMAND="EXPLICIT" ACTIVE.DOC="32018R1619" ACTIVE.LOC="AR:1;PT:4;PT:c" MOD.LEVEL="1"?><PARAG IDENTIFIER="017.003"><NO.PARAG>3.</NO.PARAG><ALINEA>Where the depositary has delegated its safekeeping functions in accordance with Article 22a of Directive 2009/65/EC to a third party located in the Union, that third party shall provide a statement to the depositary, on a regular basis, and in any case whenever a change occurs, detailing the assets of the depositary's UCITS clients.</ALINEA></PARAG><?CLG.MDFC ID="C001001M008000" IDREF="O001001M008000"?><PARAG IDENTIFIER="017.004"><NO.PARAG>4.</NO.PARAG><ALINEA>The depositary shall ensure that duties laid down in paragraphs 1 and 2 shall apply <HT TYPE="ITALIC">mutatis mutandis</HT> when the third party, to whom safekeeping functions are delegated pursuant to Article 22a of Directive 2009/65/EC, has decided to sub-delegate all or part of its safekeeping functions to another third party pursuant to the third subparagraph of Article 22a(3) of Directive 2009/65/EC.</ALINEA></PARAG></ARTICLE></DIVISION><DIVISION><TITLE><TI><P>CHAPTER 3</P></TI><STI><P><HT TYPE="BOLD">LOSS OF FINANCIAL INSTRUMENTS AND LIABILITY DISCHARGE</HT></P><P>(Article 24(1) of Directive 2009/65/EC)</P></STI></TITLE><ARTICLE IDENTIFIER="018"><TI.ART>Article 18</TI.ART><STI.ART>Loss of a financial instrument held in custody</STI.ART><PARAG IDENTIFIER="018.001"><NO.PARAG>1.</NO.PARAG><ALINEA><P>The loss of a financial instrument held in custody within the meaning of the second subparagraph of Article 24(1) of Directive 2009/65/EC shall be deemed to have taken place where, in relation to a financial instrument held in custody by the depositary or by a third party to whom the safekeeping of financial instruments has been delegated in accordance with Article 22a of Directive 2009/65/EC, any of the following conditions is met:</P><LIST TYPE="alpha"><ITEM><NP><NO.P>(a)</NO.P><TXT>a stated right of ownership of the UCITS is demonstrated not to be valid because it either ceased to exist or never existed;</TXT></NP></ITEM><ITEM><NP><NO.P>(b)</NO.P><TXT>the UCITS has been definitively deprived of its right of ownership over the financial instrument;</TXT></NP></ITEM><ITEM><NP><NO.P>(c)</NO.P><TXT>the UCITS is definitively unable to directly or indirectly dispose of the financial instrument.</TXT></NP></ITEM></LIST></ALINEA></PARAG><PARAG IDENTIFIER="018.002"><NO.PARAG>2.</NO.PARAG><ALINEA>The ascertainment by the management or the investment company of the loss of a financial instrument shall follow a documented process readily available to the competent authorities. Once a loss is ascertained, it shall be notified immediately to investors in a durable medium.</ALINEA></PARAG><?PAGE NO='18'?><PARAG IDENTIFIER="018.003"><NO.PARAG>3.</NO.PARAG><ALINEA>A financial instrument held in custody shall not be deemed to be lost within the meaning of the second subparagraph of Article 24(1) of Directive 2009/65/EC where an UCITS is definitively deprived of its right of ownership in respect of a particular instrument, as long as that instrument is substituted by or converted into another financial instrument or instruments.</ALINEA></PARAG><PARAG IDENTIFIER="018.004"><NO.PARAG>4.</NO.PARAG><ALINEA>In the event of insolvency of the third party to whom the safekeeping of financial instruments has been delegated in accordance with Article 22a of Directive 2009/65/EC, the loss of a financial instrument held in custody shall be ascertained by the management company or the investment company as soon as one of the conditions listed in paragraph 1 is met with certainty.</ALINEA><ALINEA>There shall be certainty as to whether any of the conditions set out in paragraph 1 is fulfilled at the latest at the end of the insolvency proceedings. The management company or the investment company and the depositary shall monitor closely the insolvency proceedings to determine whether all or some of the financial instruments entrusted to the third party to whom the safekeeping of financial instruments has been delegated in accordance with Article 22a of Directive 2009/65/EC are effectively lost.</ALINEA></PARAG><PARAG IDENTIFIER="018.005"><NO.PARAG>5.</NO.PARAG><ALINEA>A loss of a financial instrument held in custody shall be ascertained irrespective of whether the conditions set out in paragraph 1 are the result of fraud, negligence or other intentional or non-intentional behaviour.</ALINEA></PARAG></ARTICLE><ARTICLE IDENTIFIER="019"><TI.ART>Article 19</TI.ART><STI.ART>Liability discharge</STI.ART><PARAG IDENTIFIER="019.001"><NO.PARAG>1.</NO.PARAG><ALINEA><P>A depositary's liability under the second subparagraph of Article 24(1) of Directive 2009/65/EC shall not be triggered provided the depositary can prove that all the following conditions are met:</P><LIST TYPE="alpha"><ITEM><NP><NO.P>(a)</NO.P><TXT>the event which led to the loss is not the result of any act or omission of the depositary or of a third party to whom the safekeeping of financial instruments held in custody in accordance with point (a) of Article 22(5) of Directive 2009/65/EC has been delegated;</TXT></NP></ITEM><ITEM><NP><NO.P>(b)</NO.P><TXT>the depositary could not have reasonably prevented the occurrence of the event which led to the loss despite adopting all precautions incumbent on a diligent depositary as reflected in common industry practice;</TXT></NP></ITEM><ITEM><NP><NO.P>(c)</NO.P><TXT>the depositary could not have prevented the loss despite rigorous and comprehensive due diligence as documented by:</TXT><P><LIST TYPE="roman"><ITEM><NP><NO.P>(i)</NO.P><TXT>establishing, implementing, applying and maintaining structures and procedures and insuring expertise that are adequate and proportionate to the nature and complexity of the assets of the UCITS in order to identify in a timely manner and monitor on an ongoing basis external events which may result in loss of a financial instrument held in custody;</TXT></NP></ITEM><ITEM><NP><NO.P>(ii)</NO.P><TXT>assessing on an ongoing basis whether any of the events identified under point (i) presents a significant risk of loss of a financial instrument held in custody;</TXT></NP></ITEM><?PAGE NO='19'?><ITEM><NP><NO.P>(iii)</NO.P><TXT>informing the management company or the investment company of the significant risks identified and taking appropriate actions, if any, to prevent or mitigate the loss of financial instruments held in custody, where actual or potential external events have been identified which are believed to present a significant risk of loss of a financial instrument held in custody.</TXT></NP></ITEM></LIST></P></NP></ITEM></LIST></ALINEA></PARAG><PARAG IDENTIFIER="019.002"><NO.PARAG>2.</NO.PARAG><ALINEA><P>The requirements referred to in points (a) and (b) of paragraph 1 may be deemed to be fulfilled in the following circumstances:</P><LIST TYPE="alpha"><ITEM><NP><NO.P>(a)</NO.P><TXT>natural events beyond human control or influence;</TXT></NP></ITEM><ITEM><NP><NO.P>(b)</NO.P><TXT>the adoption of any law, decree, regulation, decision or order by any government or governmental body, including any court or tribunal, which impacts the financial instruments held in custody;</TXT></NP></ITEM><ITEM><NP><NO.P>(c)</NO.P><TXT>war, riots or other major upheavals.</TXT></NP></ITEM></LIST></ALINEA></PARAG><PARAG IDENTIFIER="019.003"><NO.PARAG>3.</NO.PARAG><ALINEA>The requirements referred to in points (a) and (b) of paragraph 1 shall not be deemed to be fulfilled in cases such as an accounting error, operational failure, fraud, failure to apply the segregation requirements at the level of the depositary or a third party to whom the safekeeping of financial instruments held in custody in accordance with point (a) of Article 22(5) of Directive 2009/65/EC has been delegated.</ALINEA></PARAG></ARTICLE></DIVISION><DIVISION><TITLE><TI><P>CHAPTER 4</P></TI><STI><P><HT TYPE="BOLD">INDEPENDENCE REQUIREMENTS AND FINAL PROVISIONS</HT></P><P>(Article 25 of Directive 2009/65/EC)</P></STI></TITLE><ARTICLE IDENTIFIER="020"><TI.ART>Article 20</TI.ART><STI.ART>Management body</STI.ART><ALINEA>For the purposes of this Chapter 'management body of the management company' shall include the management body of the management company or the management body of the investment company.</ALINEA></ARTICLE><ARTICLE IDENTIFIER="021"><TI.ART>Article 21</TI.ART><STI.ART>Common management</STI.ART><ALINEA><P>The management company or the investment company and the depositary shall at all times comply with all of the following requirements:</P><LIST TYPE="alpha"><ITEM><NP><NO.P>(a)</NO.P><TXT>no person may at the same time be both a member of the management body of the management company and a member of the management body of the depositary;</TXT></NP></ITEM><ITEM><NP><NO.P>(b)</NO.P><TXT>no person may at the same time be both a member of the management body of the management company and an employee of the depositary;</TXT></NP></ITEM><ITEM><NP><NO.P>(c)</NO.P><TXT>no person may at the same time be both a member of the management body of the depositary and an employee of the management company or the investment company;</TXT></NP></ITEM><?PAGE NO='20'?><ITEM><NP><NO.P>(d)</NO.P><TXT>where the management body of the management company is not in charge of the supervisory functions within the company, no more than one third of the members of its body in charge of the supervisory functions shall consist of members who are at the same time members of the management body, the body in charge of the supervisory functions or employees of the depositary;</TXT></NP></ITEM><ITEM><NP><NO.P>(e)</NO.P><TXT>where the management body of the depositary is not in charge of the supervisory functions within the depositary, no more than one third of the members of its body in charge of the supervisory functions shall consist of members who are at the same time members of the management body of the management company, or the body in charge of the supervisory functions of the management company or of the investment company or employees of the management company or of the investment company.</TXT></NP></ITEM></LIST></ALINEA></ARTICLE><ARTICLE IDENTIFIER="022"><TI.ART>Article 22</TI.ART><STI.ART>Appointment of depositary and delegation of safekeeping</STI.ART><PARAG IDENTIFIER="022.001"><NO.PARAG>1.</NO.PARAG><ALINEA>The management company or the investment company shall have in place a decision-making process for choosing and appointing the depositary, which shall be based on objective pre-defined criteria and meet the sole interest of the UCITS and the investors of the UCITS.</ALINEA></PARAG><PARAG IDENTIFIER="022.002"><NO.PARAG>2.</NO.PARAG><ALINEA><P>Where the management company or the investment company appoints a depositary to which it has a link or a group link, it shall keep documentary evidence of the following:</P><LIST TYPE="alpha"><ITEM><NP><NO.P>(a)</NO.P><TXT>an assessment comparing the merits of appointing a depositary with a link or a group link with the merits of appointing a depositary which has no link or no group link with the management company or the investment company, taking into account at least the costs, the expertise, financial standing and the quality of services provided by all depositaries assessed;</TXT></NP></ITEM><ITEM><NP><NO.P>(b)</NO.P><TXT>a report, based on the assessment referred to in point (a), describing the way in which the appointment meets the objective pre-defined criteria referred to in paragraph 1 and is made in the sole interest of the UCITS and the investors of the UCITS.</TXT></NP></ITEM></LIST></ALINEA></PARAG><PARAG IDENTIFIER="022.003"><NO.PARAG>3.</NO.PARAG><ALINEA><?CLG.MDFO ID="O001001M009000" IDREF="C001001M009000" ACTION="REPLACED" LEVEL="TEXT" COMMAND="EXPLICIT" ACTIVE.DOC="32018R1619" ACTIVE.LOC="AR:1;PT:5" MOD.LEVEL="1"?>The management company or the investment company shall demonstrate to the competent authority of the UCITS home Member State that it is satisfied with the appointment of the depositary and that the appointment is in the sole interest of the UCITS and the investors of the UCITS. The management company or the investment company shall make the documentary evidence referred to in paragraph 2 available to the competent authority of the UCITS home Member State.<?CLG.MDFC ID="C001001M009000" IDREF="O001001M009000"?></ALINEA></PARAG><PARAG IDENTIFIER="022.004"><NO.PARAG>4.</NO.PARAG><ALINEA>The management company or the investment company shall justify to investors of the UCITS, upon request, the choice of the depositary.</ALINEA></PARAG><PARAG IDENTIFIER="022.005"><NO.PARAG>5.</NO.PARAG><ALINEA>The depositary shall have in place a decision-making process for choosing third parties to whom it may delegate the safekeeping functions in accordance with Article 22a of Directive 2009/65/EC, which shall be based on objective pre-defined criteria and meet the sole interest of the UCITS and the investors of the UCITS.</ALINEA></PARAG></ARTICLE><?PAGE NO='21'?><ARTICLE IDENTIFIER="023"><TI.ART>Article 23</TI.ART><STI.ART>Conflicts of interest</STI.ART><ALINEA><P>Where a link or a group link exists between them, the management company or the investment company and the depositary, shall put in place policies and procedures ensuring that they:</P><LIST TYPE="alpha"><ITEM><NP><NO.P>(a)</NO.P><TXT>identify all conflicts of interest arising from that link;</TXT></NP></ITEM><ITEM><NP><NO.P>(b)</NO.P><TXT>take all reasonable steps to avoid those conflicts of interest.</TXT></NP></ITEM></LIST></ALINEA><ALINEA>Where a conflict of interest referred to in the first subparagraph cannot be avoided, the management company or the investment company and the depositary shall manage, monitor and disclose that conflict of interest in order to prevent adverse effects on the interests of the UCITS and of the investors of the UCITS.</ALINEA></ARTICLE><ARTICLE IDENTIFIER="024"><TI.ART>Article 24</TI.ART><STI.ART>Independence of management boards and supervisory functions</STI.ART><PARAG IDENTIFIER="024.001"><NO.PARAG>1.</NO.PARAG><ALINEA><P>Where a group link exists between them, the management company or the investment company and the depositary shall ensure that:</P><LIST TYPE="alpha"><ITEM><NP><NO.P>(a)</NO.P><TXT>where the management body of the management company and the management body of the depositary are also in charge of the supervisory functions within the respective companies, at least one third of the members or two persons, whichever is lower, on the management body of the management company and on the management body of the depositary shall be independent;</TXT></NP></ITEM><ITEM><NP><NO.P>(b)</NO.P><TXT>where the management body of the management company and the management body of the depositary are not in charge of the supervisory functions within the respective companies, at least one third of the members or two persons, whichever is lower, on the body in charge of the supervisory functions within the management company and within the depositary shall be independent.</TXT></NP></ITEM></LIST></ALINEA></PARAG><PARAG IDENTIFIER="024.002"><NO.PARAG>2.</NO.PARAG><ALINEA>For the purposes of the first paragraph, members of the management body of the management company, members of the management body of the depositary or members of the body in charge of the supervisory functions of the above companies shall be deemed independent as long as they are neither members of the management body or the body in charge of the supervisory functions nor employees of any of the other undertakings between which a group link exists and are free of any business, family or other relationship with the management company or the investment company, the depositary and any other undertaking within the group that gives rise to a conflict of interest such as to impair their judgment.</ALINEA></PARAG></ARTICLE><ARTICLE IDENTIFIER="025"><TI.ART>Article 25</TI.ART><STI.ART>Entry into force and application</STI.ART><ALINEA>This Regulation shall enter into force on the twentieth day following that of its publication in the <HT TYPE="ITALIC">Official Journal of the European Union</HT>.</ALINEA><ALINEA>It shall apply from <DATE ISO="20161013">13 October 2016</DATE>.</ALINEA></ARTICLE></DIVISION></ENACTING.TERMS><FINAL><P>This Regulation shall be binding in its entirety and directly applicable in all Member States.</P></FINAL></CONS.DOC></CONS.ACT>