<?xml version="1.0" encoding="UTF-8"?>
<ACT xmlns:xsi="http://www.w3.org/2001/XMLSchema-instance" xmlns:fmx="http://opoce" xsi:noNamespaceSchemaLocation="http://formex.publications.europa.eu/schema/formex-05.55-20141201.xd"><BIB.INSTANCE><DOCUMENT.REF FILE="L_2016021EN.01000201.doc.xml"><COLL>L</COLL><NO.OJ>021</NO.OJ><YEAR>2016</YEAR><LG.OJ>EN</LG.OJ><PAGE.FIRST>2</PAGE.FIRST><PAGE.SEQ>1</PAGE.SEQ><VOLUME.REF>01</VOLUME.REF></DOCUMENT.REF><EEA/><DATE ISO="20151016">20151016</DATE><LG.DOC>EN</LG.DOC><NO.SEQ>0002</NO.SEQ><PAGE.FIRST>2</PAGE.FIRST><PAGE.SEQ>1</PAGE.SEQ><PAGE.LAST>20</PAGE.LAST><PAGE.TOTAL>19</PAGE.TOTAL><NO.DOC FORMAT="YN" TYPE="OJ"><NO.CURRENT>98</NO.CURRENT><YEAR>2016</YEAR><COM>EU</COM></NO.DOC></BIB.INSTANCE><TITLE><TI><P><HT TYPE="UC">Commission Delegated Regulation</HT> (EU) 2016/98</P><P>of <DATE ISO="20151016">16 October 2015</DATE></P><P>supplementing Directive 2013/36/EU of the European Parliament and of the Council with regard to regulatory technical standards for specifying the general conditions for the functioning of colleges of supervisors</P><P>(Text with EEA relevance)</P></TI></TITLE><PREAMBLE><PREAMBLE.INIT>THE EUROPEAN COMMISSION,</PREAMBLE.INIT><GR.VISA><VISA>Having regard to the Treaty on the Functioning of the European Union,</VISA><VISA>Having regard to Directive 2013/36/EU of <DATE ISO="20130626">26 June 2013</DATE> of the European Parliament and of the Council on access to the activity of credit institutions and the prudential supervision of credit institutions and investment firms, amending Directive 2002/87/EC and repealing Directives 2006/48/EC and 2006/49/EC<NOTE NOTE.ID="E0001" NUMBERING="ARAB" TYPE="FOOTNOTE"><P><REF.DOC.OJ COLL="L" DATE.PUB="20130627" NO.OJ="176" PAGE.FIRST="338">OJ L 176, 27.6.2013, p. 338</REF.DOC.OJ>.</P></NOTE>, and in particular to Article 51(4) and Article 116(4) thereof,</VISA></GR.VISA><GR.CONSID><GR.CONSID.INIT>Whereas:</GR.CONSID.INIT><CONSID><NP><NO.P>(1)</NO.P><TXT>The performance of the mapping of a group of institutions, which would identify the group entities in the Union or a third country and which would describe for each group entity its nature, location, the authorities involved in its supervision, the applicable prudential exemptions, its importance for the group and importance for the country in which it is authorised or established as well the criteria for determining that importance, is considered as a vital element for the identification of college members and potential observers. In this context, information on the importance of a branch for the group and importance of that branch for the Member State in which it is established is essential in order to determine the participation of the competent authorities of that Member State in college activities. Information on the nature of the group entities, whether institutions, branches or other financial sector entities, as well as on their country of authorisation or establishment, whether a Member State or a third country, is also important for identifying college members and potential observers.</TXT></NP></CONSID><CONSID><NP><NO.P>(2)</NO.P><TXT>Information on the importance of a group entity for the group and its importance for the Member State in which it is authorised or established is essential for determining the level of engagement of the competent authority of that Member State in the activities of the college, and, in particular, for carrying out the supervisory review and evaluation process.</TXT></NP></CONSID><CONSID><NP><NO.P>(3)</NO.P><TXT>The written coordination and cooperation arrangements referred to in Article 115 of Directive 2013/36/EU should cover all areas of college work to strengthen the efficiency of supervisory colleges. The written arrangements should also cover arrangements between some college members involved in specific college activities such as those performed through specific substructures of the college. The written arrangements should also include operational aspects of college work as these aspects are essential for facilitating the functioning of the college both in going concern and during emergency situations. As it is essential to ensure cooperation within the college before and for the purpose of providing input for group resolution issues, the written arrangements should provide for the processes of coordinating the relevant input as well as the responsibilities and role of the consolidating supervisor in communicating that input through the group-level resolution authority as defined in Article 2(1)(44) of Directive 2014/59/EU of the European Parliament and of the Council<NOTE NOTE.ID="E0002" NUMBERING="ARAB" TYPE="FOOTNOTE"><P>Directive 2014/59/EU of the European Parliament and of the Council of <DATE ISO="20140515">15 May 2014</DATE> establishing a framework for the recovery and resolution of credit institutions and investment firms and amending Council Directive 82/891/EEC, and Directives 2001/24/EC, 2002/47/EC, 2004/25/EC, 2005/56/EC, 2007/36/EC, 2011/35/EU, 2012/30/EU and 2013/36/EU, and Regulations (EU) No 1093/2010 and (EU) No 648/2012, of the European Parliament and of the Council (<REF.DOC.OJ COLL="L" DATE.PUB="20140612" NO.OJ="173" PAGE.FIRST="190">OJ L 173, 12.6.2014, p. 190</REF.DOC.OJ>).</P></NOTE> to the resolution college. The written arrangements should be comprehensive, coherent and<?PAGE NO="3"?> exhaustive and should provide an adequate and appropriate basis to the competent authorities in order for them to discharge their relevant duties and tasks within, rather than outside the college.</TXT></NP></CONSID><CONSID><NP><NO.P>(4)</NO.P><TXT>Colleges are a key tool for exchanging information, anticipating and dealing with emergency situations, and enabling the consolidating supervisor to conduct effective supervision on a consolidated basis. To ensure consistency and enable the EBA to perform its tasks as provided for in Regulation (EU) No 1093/2010 of the European Parliament and of the Council<NOTE NOTE.ID="E0003" NUMBERING="ARAB" TYPE="FOOTNOTE"><P>Regulation (EU) No 1093/2010 of the European Parliament and of the Council of <DATE ISO="20101124">24 November 2010</DATE> establishing a European Supervisory Authority (European Banking Authority), amending Decision No 716/2009/EC and repealing Commission Decision 2009/78/EC (<REF.DOC.OJ COLL="L" DATE.PUB="20101215" NO.OJ="331" PAGE.FIRST="1">OJ L 331, 15.12.2010, p. 1</REF.DOC.OJ>).</P></NOTE> and in Article 116 of Directive 2013/36/EU, it is appropriate for the EBA to participate in all colleges as a member.</TXT></NP></CONSID><CONSID><NP><NO.P>(5)</NO.P><TXT>In order to perform all college activities, the consolidating supervisor and the other members of the college should have an overview of the activities carried out by all group entities, including by those carrying out financial activities without being qualified as institutions and by those operating outside the Union. Interaction between the consolidating supervisor, college members, third-country supervisory authorities, public authorities or bodies which are responsible for or involved in the supervision of a group entity, including authorities responsible for the prudential supervision of the group's financial sector entities or competent authorities responsible for the supervision of markets in financial instruments, the prevention of the use of the financial system for the purpose of money laundering and terrorist financing, or consumer protection, should be promoted by allowing these third-country supervisory authorities and public authorities or bodies to participate in college work as observers, as appropriate.</TXT></NP></CONSID><CONSID><NP><NO.P>(6)</NO.P><TXT>College members should discuss and agree on the scope and level of involvement of observers, if any, in the college. The framework of participation of observers in the college should be clearly stated in the written coordination and cooperation arrangements and should be communicated to the observers.</TXT></NP></CONSID><CONSID><NP><NO.P>(7)</NO.P><TXT>Members of the college of supervisors should work together, coordinating their supervisory actions to the maximum extent possible and cooperating closely in order to better perform their duties, to avoid duplication of tasks, including duplication of information requests addressed to the supervised entities of the group. In this context, agreements on entrustment of tasks and delegation of responsibilities should be considered on a regular basis by the members of the college, and at least when college members develop their college supervisory examination programme.</TXT></NP></CONSID><CONSID><NP><NO.P>(8)</NO.P><TXT>The consolidating supervisor should have access to all information necessary for the performance of its tasks and responsibilities and should act as the coordinator for the collection and dissemination of information received from any college member or observer or from any entity of the group, or any input received from the resolution college, in particular from the relevant group-level resolution authority. The same applies also for the members of the college. In particular, where the consolidating supervisor determines the relevance of particular information for another member of the college, including the competent authority in a host Member State where a significant branch is established, it should refrain from unjustifiably excluding members of the college from receiving information.</TXT></NP></CONSID><CONSID><NP><NO.P>(9)</NO.P><TXT>Members of the college participating in the performance of the tasks referred to in Article 113 of Directive 2013/36/EU should be encouraged to exchange information on the assessment of the main elements of the supervisory review and evaluation process as referred to in Article 97 of that Directive, recognising at the same time that the supervisory review and evaluation process may be performed differently across Member States depending on the transposition of those Union rules into the national legislation taking also into account the guidelines issued by the EBA under Article 107(3) of Directive 2013/36/EU.</TXT></NP></CONSID><CONSID><NP><NO.P>(10)</NO.P><TXT>To facilitate cooperation between competent authorities and to coordinate any decisions intended to address issues of compliance by an institution with the requirements regarding approaches that need permission by competent authorities before being used for the calculation of own fund requirements (use of internal models for credit risk, market risk, counterparty risk and operational risk), the conditions of cooperation between the consolidating supervisor and the relevant competent authorities for exchanging information on the performance of those internal approaches, and for discussing and reaching agreement on measures to address inefficiencies identified should be specified.</TXT></NP></CONSID><?PAGE NO="4"?><CONSID><NP><NO.P>(11)</NO.P><TXT>To facilitate the identification of early warning signs, potential risks and vulnerabilities for the group and its entities and for the system in which they operate, college members are expected to exchange quantitative information, for the group and its entities, in a consistent and comparable way. This information should cover main areas of the information collected by the competent authorities in accordance with Commission Implementing Regulation (EU) No 680/2014<NOTE NOTE.ID="E0004" NUMBERING="ARAB" TYPE="FOOTNOTE"><P>Commission Implementing Regulation (EU) No 680/2014 of <DATE ISO="20140416">16 April 2014</DATE> laying down implementing technical standards with regard to supervisory reporting of institutions according to Regulation (EU) No 575/2013 of the European Parliament and of the Council (<REF.DOC.OJ COLL="L" DATE.PUB="20140628" NO.OJ="191" PAGE.FIRST="1">OJ L 191, 28.6.2014, p. 1</REF.DOC.OJ>).</P></NOTE> specifying the uniform formats, frequencies, dates of reporting, definitions and the IT solutions to be applied by the institutions for supervisory reporting purposes, and should be exchanged while the competent authorities are in the process of developing the group risk assessment report and reaching the joint decisions on capital and liquidity pursuant to Article 113 of Directive 2013/36/EU. Each college should decide on the exact set of information to be exchanged for these purposes.</TXT></NP></CONSID><CONSID><NP><NO.P>(12)</NO.P><TXT>To develop the college supervisory examination programme, college members shall take into account the group risk assessment report and the outcome of the capital and liquidity joint decision so as to better identify the priorities of common work. Thus, the development of the college supervisory examination programme should start once the group risk assessment and joint decision process have been concluded, while for its finalisation the competent authorities should consider the tasks they have committed to perform at national level, the resources allocated to those tasks and the respective timelines for their performance.</TXT></NP></CONSID><CONSID><NP><NO.P>(13)</NO.P><TXT>Members of the college should coordinate their activities in preparation for and during emergency situations such as adverse developments which may seriously jeopardise the orderly function and the integrity of the financial markets or the stability of the whole or part of the financial system of the Union, or other situations that affect or might explicitly affect the financial and economic situation of a banking group or any of its subsidiaries. Therefore, the planning and coordination of the competent authorities' activities in preparation for and during emergency situations should include, but not be limited to the activities referred to in the relevant provisions of Directive 2014/59/EU; in particular activities aiming at coordinating the group recovery planning and at providing coordinated input to resolution authorities, where needed, should be seen as examples of activities in preparation for and during emergency situations.</TXT></NP></CONSID><CONSID><NP><NO.P>(14)</NO.P><TXT>When dealing with an emergency situation, college members, under the coordination of the consolidating supervisor, should aim to develop a coordinated supervisory assessment of the situation, agree on a coordinated supervisory response and monitor the implementation of their response to ensure that the emergency situation is properly assessed and addressed. They should also ensure that any external communication is done in a coordinated way and covers elements which are agreed <HT TYPE="ITALIC">ex-ante</HT> between the members of the college.</TXT></NP></CONSID><CONSID><NP><NO.P>(15)</NO.P><TXT>The provisions in this Regulation are closely linked to one another, since they deal with the general conditions of the functioning of the colleges of supervisors. To ensure coherence between those provisions, which should enter into force at the same time, and to facilitate a comprehensive view and compact access to them by persons subject to those obligations it is desirable to include all the regulatory technical standards required by Article 51(4) and 116(4) of Directive 2013/36/EU in a single Regulation.</TXT></NP></CONSID><CONSID><NP><NO.P>(16)</NO.P><TXT>As the vast majority of supervisory colleges across the EU are formed in accordance with Article 116 of Directive 2013/36/EU it appears more appropriate to first specify the conditions regarding colleges under Article 116 of Directive 2013/36/EU before specifying those regarding colleges under Article 51 of Directive 2013/36/EU, the former appearing more as a general case, the latter as a special case.</TXT></NP></CONSID><CONSID><NP><NO.P>(17)</NO.P><TXT>This Regulation is based on the draft regulatory technical standards submitted by the European supervisory authority (European Banking Authority) (EBA) to the Commission.</TXT></NP></CONSID><CONSID><NP><NO.P>(18)</NO.P><TXT>The EBA has conducted open public consultations on the draft regulatory technical standards on which this Regulation is based, analysed the potential related costs and benefits and requested the opinion of the Banking Stakeholder Group established in accordance with Article 37 of Regulation (EU) No 1093/2010,</TXT></NP></CONSID></GR.CONSID><?PAGE NO="5"?><PREAMBLE.FINAL>HAS ADOPTED THIS REGULATION:</PREAMBLE.FINAL></PREAMBLE><ENACTING.TERMS><DIVISION><TITLE><TI><P>CHAPTER 1</P></TI><STI><P><HT TYPE="BOLD">GENERAL PROVISIONS</HT></P></STI></TITLE><ARTICLE IDENTIFIER="001"><TI.ART>Article 1</TI.ART><STI.ART>Subject matter</STI.ART><ALINEA>This Regulation specifies the general conditions of functioning of the college of supervisors (<QUOT.START CODE="2018" ID="QS0001" REF.END="QE0001"/>college<QUOT.END CODE="2019" ID="QE0001" REF.START="QS0001"/>) formed in accordance with Article 116 and Article 51(3) of Directive 2013/36/EU.</ALINEA></ARTICLE></DIVISION><DIVISION><TITLE><TI><P>CHAPTER 2</P></TI><STI><P><HT TYPE="BOLD">CONDITIONS REGARDING THE FUNCTIONING OF COLLEGES FORMED IN ACCORDANCE WITH ARTICLE 116 OF DIRECTIVE 2013/36/EU</HT></P></STI></TITLE><DIVISION><TITLE><TI><P><HT TYPE="ITALIC">SECTION 1</HT></P></TI><STI><P><HT TYPE="BOLD"><HT TYPE="ITALIC">Establishment and functioning of colleges</HT></HT></P></STI></TITLE><ARTICLE IDENTIFIER="002"><TI.ART>Article 2</TI.ART><STI.ART>Establishment of the mapping of a group of institutions</STI.ART><PARAG IDENTIFIER="002.001"><NO.PARAG>1.</NO.PARAG><ALINEA>For the purpose of identifying the members and potential observers of the supervisory college, the consolidating supervisor shall establish the mapping of a group of institutions in accordance with Article 2 of Commission Implementing Regulation (EU) 2016/99<NOTE NOTE.ID="E0005" NUMBERING="ARAB" TYPE="FOOTNOTE"><P>Commission Implementing Regulation (EU) 2016/99 of <DATE ISO="20151016">16 October 2015</DATE> laying down implementing technical standards with regard to determining the operational functioning of the colleges of supervisors according to Directive 2013/36/EU of the European Parliament and of the Council (see page 21 of this Official Journal).</P></NOTE>.</ALINEA></PARAG><PARAG IDENTIFIER="002.002"><NO.PARAG>2.</NO.PARAG><ALINEA><P>The mapping of a group of institutions shall result in the identification of the following group entities:</P><LIST TYPE="alpha"><ITEM><NP><NO.P>(a)</NO.P><TXT>institutions authorised and branches established in a Member State;</TXT></NP></ITEM><ITEM><NP><NO.P>(b)</NO.P><TXT>financial sector entities authorised in a Member State;</TXT></NP></ITEM><ITEM><NP><NO.P>(c)</NO.P><TXT>institutions authorised and branches established in a third country.</TXT></NP></ITEM></LIST></ALINEA></PARAG><PARAG IDENTIFIER="002.003"><NO.PARAG>3.</NO.PARAG><ALINEA><P>The following information shall be reflected in the mapping for each institution authorised and branch established in a Member State:</P><LIST TYPE="alpha"><ITEM><NP><NO.P>(a)</NO.P><TXT>the Member State where the institution is authorised or the branch established;</TXT></NP></ITEM><ITEM><NP><NO.P>(b)</NO.P><TXT>the competent authority responsible for the supervision of the institution or the competent authority of the host Member State where the branch is established as well as other financial sector authorities of that Member State, such as competent authorities responsible for the supervision of markets in financial instruments, the prevention of the use of the financial system for the purpose of money laundering and terrorist financing, or consumer protection;</TXT></NP></ITEM><ITEM><NP><NO.P>(c)</NO.P><TXT>for an institution, including for a subsidiary of an EU parent undertaking established in the same Member State as well as for the EU parent undertaking itself, information as to whether the institution is subject to prudential supervision on an individual basis or whether it has been granted a waiver from the application of requirements set out in Parts Two to Eight of Regulation (EU) No 575/2013 of the European Parliament and of the Council<NOTE NOTE.ID="E0006" NUMBERING="ARAB" TYPE="FOOTNOTE"><P>Regulation (EU) No 575/2013 of the European Parliament and of the Council of <DATE ISO="20130626">26 June 2013</DATE> on prudential requirements for credit institutions and investment firms and amending Regulation (EU) No 648/2012 (<REF.DOC.OJ COLL="L" DATE.PUB="20130627" NO.OJ="176" PAGE.FIRST="1">OJ L 176, 27.6.2013, p. 1</REF.DOC.OJ>).</P></NOTE> on an individual basis pursuant to Articles 7, 8, or 10 of that Regulation;</TXT></NP></ITEM><?PAGE NO="6"?><ITEM><NP><NO.P>(d)</NO.P><TXT>for an institution, information relating to the importance of the institution for the Member State where it is authorised and the relevant criteria used by the competent authorities to determine this importance as well as information on the importance of that institution for the group, provided that the total amount of assets and off-balance sheet items of that institution exceeds 1 % of the group's total assets and off balance sheet items on consolidated basis;</TXT></NP></ITEM><ITEM><NP><NO.P>(e)</NO.P><TXT>for a branch, information relating to the importance of the branch for the Member State where it is established, in particular whether this branch has been designated or is proposed to be designated as significant in accordance with Article 51 of Directive 2013/36/EU, as well as information on the importance of that branch for the group, provided that the total amount of assets and off-balance sheet items of that branch exceeds 1 % of the group's total assets and off balance sheet items on consolidated basis.</TXT></NP></ITEM></LIST></ALINEA></PARAG><PARAG IDENTIFIER="002.004"><NO.PARAG>4.</NO.PARAG><ALINEA><P>The following information shall be reflected in the mapping for each financial sector entity, institution or branch referred to in points (b) and (c) of paragraph 2:</P><LIST TYPE="alpha"><ITEM><NP><NO.P>(a)</NO.P><TXT>the Member State where the financial sector entity is authorised or the third country where the institution is authorised or the branch is established;</TXT></NP></ITEM><ITEM><NP><NO.P>(b)</NO.P><TXT>the authority responsible for or involved in the supervision of that financial sector entity, institution or branch;</TXT></NP></ITEM><ITEM><NP><NO.P>(c)</NO.P><TXT>information on the importance of the financial sector entity, of the institution or of the branch for the group, provided that the total amount of assets and off-balance sheet items of that financial sector entity, institution or branch exceeds 1 % of the group's total assets and off balance sheet items on consolidated basis.</TXT></NP></ITEM></LIST></ALINEA></PARAG></ARTICLE><ARTICLE IDENTIFIER="003"><TI.ART>Article 3</TI.ART><STI.ART>Designation of the members and observers of a college</STI.ART><PARAG IDENTIFIER="003.001"><NO.PARAG>1.</NO.PARAG><ALINEA><P>The consolidating supervisor shall invite the following authorities to become members of the college:</P><LIST TYPE="alpha"><ITEM><NP><NO.P>(a)</NO.P><TXT>the competent authorities responsible for the supervision of institutions which are subsidiaries of an EU parent institution or of an EU parent financial holding company or of an EU parent mixed financial holding company and the competent authorities of host Member States where significant branches as referred to in Article 51 of Directive 2013/36/EU are established;</TXT></NP></ITEM><ITEM><NP><NO.P>(b)</NO.P><TXT>the ESCB central banks of Member States that are involved in accordance with their national law in the prudential supervision of the legal entities referred to in point a, but which are not competent authorities;</TXT></NP></ITEM><ITEM><NP><NO.P>(c)</NO.P><TXT>the EBA.</TXT></NP></ITEM></LIST></ALINEA></PARAG><PARAG IDENTIFIER="003.002"><NO.PARAG>2.</NO.PARAG><ALINEA>The consolidating supervisor may invite the competent authorities of host Member States where non-significant branches are established to participate in the college as observers in accordance with the process determined in Article 3(1)(b) of Implementing Regulation (EU) 2016/99.</ALINEA></PARAG><PARAG IDENTIFIER="003.003"><NO.PARAG>3.</NO.PARAG><ALINEA>The consolidating supervisor may invite the supervisory authorities of third countries where institutions are authorised or branches are established to participate in the college as observers in accordance with the process determined in Article 3(1)(c) of Implementing Regulation (EU) 2016/99.</ALINEA></PARAG><PARAG IDENTIFIER="003.004"><NO.PARAG>4.</NO.PARAG><ALINEA><P>The consolidating supervisor may invite the following authorities to participate in the college as observers in accordance with the process determined in Article 3(1)(d) of Implementing Regulation (EU) 2016/99:</P><LIST TYPE="alpha"><ITEM><NP><NO.P>(a)</NO.P><TXT>the ESCB central banks which are not empowered by national law to supervise an institution authorised or a branch established in a Member State;</TXT></NP></ITEM><?PAGE NO="7"?><ITEM><NP><NO.P>(b)</NO.P><TXT>the public authorities or bodies in a Member State, which are responsible for or involved in the supervision of a group entity, including authorities responsible for the prudential supervision of the group's financial sector entities or competent authorities responsible for the supervision of markets in financial instruments, the prevention of the use of the financial system for the purpose of money laundering and terrorist financing, or consumer protection.</TXT></NP></ITEM></LIST></ALINEA></PARAG><PARAG IDENTIFIER="003.005"><NO.PARAG>5.</NO.PARAG><ALINEA>The consolidating supervisor and the members of the college shall specify the arrangements covering the participation of the observers in the college in the written coordination and cooperation arrangements referred to in Article 5(c). The consolidating supervisor shall notify these arrangements to the observers.</ALINEA></PARAG></ARTICLE><ARTICLE IDENTIFIER="004"><TI.ART>Article 4</TI.ART><STI.ART>Communication of the setting up and composition of a college</STI.ART><ALINEA>The consolidating supervisor shall communicate to the EU parent undertaking of the group the establishment of a college and the identity of its members and observers, as well as any changes in that composition.</ALINEA></ARTICLE><ARTICLE IDENTIFIER="005"><TI.ART>Article 5</TI.ART><STI.ART>Establishment of the written coordination and cooperation arrangements</STI.ART><ALINEA><P>The written coordination and cooperation arrangements referred to in Article 115 of Directive 2013/36/EU shall include at least the following:</P><LIST TYPE="alpha"><ITEM><NP><NO.P>(a)</NO.P><TXT>information on the overall structure of the group covering all group entities;</TXT></NP></ITEM><ITEM><NP><NO.P>(b)</NO.P><TXT>identification of the members and observers of the college;</TXT></NP></ITEM><ITEM><NP><NO.P>(c)</NO.P><TXT>a description of the terms covering the participation of observers in the college as referred to in Article 3(5) of this Regulation, including their involvement in the various dialogues and processes of the college and their rights and obligations with regard to exchanging information;</TXT></NP></ITEM><ITEM><NP><NO.P>(d)</NO.P><TXT>a description of the arrangements for exchanging information including their scope, frequency and channels of communication;</TXT></NP></ITEM><ITEM><NP><NO.P>(e)</NO.P><TXT>a description of the arrangements for the treatment of confidential information;</TXT></NP></ITEM><ITEM><NP><NO.P>(f)</NO.P><TXT>a description of the arrangements on entrustment of tasks and on delegation of responsibilities, where relevant;</TXT></NP></ITEM><ITEM><NP><NO.P>(g)</NO.P><TXT>a description of any substructures of the college;</TXT></NP></ITEM><ITEM><NP><NO.P>(h)</NO.P><TXT>a description of the framework for the planning and coordination of supervisory activities in going concern situations;</TXT></NP></ITEM><ITEM><NP><NO.P>(i)</NO.P><TXT>a description of the framework for the planning and coordination of supervisory activities in preparation for and during emergency situations, including contingency planning, communication tools and procedures;</TXT></NP></ITEM><ITEM><NP><NO.P>(j)</NO.P><TXT>a description of the communication policy of the consolidating supervisor and the members of the college with the EU parent undertaking and with the group entities;</TXT></NP></ITEM><ITEM><NP><NO.P>(k)</NO.P><TXT>agreed procedures and deadlines to be followed for the circulation of the meeting documents;</TXT></NP></ITEM><ITEM><NP><NO.P>(l)</NO.P><TXT>any other agreement between the college members, including agreed indicators for identifying the early warning signs, potential risks and vulnerabilities;</TXT></NP></ITEM><ITEM><NP><NO.P>(m)</NO.P><TXT>a description of the framework for providing coordinated input to the resolution college, in particular for providing coordinated input without restriction for the purposes of the consultation process referred to in Articles 12, 13, 16, 18, 91 and 92 of Directive 2014/59/EU;</TXT></NP></ITEM><?PAGE NO="8"?><ITEM><NP><NO.P>(n)</NO.P><TXT>a description of the role of the consolidating supervisor in particular with regard to coordinating the provision of the input referred to in point (m) through the group-level resolution authority to the relevant resolution college;</TXT></NP></ITEM><ITEM><NP><NO.P>(o)</NO.P><TXT>provisions covering arrangements where a member or an observer terminates its participation in the college.</TXT></NP></ITEM></LIST></ALINEA></ARTICLE><ARTICLE IDENTIFIER="006"><TI.ART>Article 6</TI.ART><STI.ART>Participation in college meetings and activities</STI.ART><PARAG IDENTIFIER="006.001"><NO.PARAG>1.</NO.PARAG><ALINEA><P>When deciding which authorities shall participate in a college meeting or activity in accordance with Article 116(7) of Directive 2013/36/EU, the consolidating supervisor shall take into account the following:</P><LIST TYPE="alpha"><ITEM><NP><NO.P>(a)</NO.P><TXT>the topics to be discussed and the objective of the meeting or activity, in particular with regard to their relevance for each group entity;</TXT></NP></ITEM><ITEM><NP><NO.P>(b)</NO.P><TXT>the importance of the group entity for the Member State where the group entity is authorised or established, and its importance for the group.</TXT></NP></ITEM></LIST></ALINEA></PARAG><PARAG IDENTIFIER="006.002"><NO.PARAG>2.</NO.PARAG><ALINEA>The consolidating supervisor and the members of the college shall ensure that the most appropriate representatives participate in the college meetings or activities, based on the topics discussed and objectives pursued. Those representatives shall have the power to commit their authorities as members of the college, to the maximum extent possible, for the decisions planned to be taken during the meetings or activities.</ALINEA></PARAG><PARAG IDENTIFIER="006.003"><NO.PARAG>3.</NO.PARAG><ALINEA>The consolidating supervisor may invite representatives of group entities to participate in a college meeting or activity, based on the topics and objectives of the college meeting or activity.</ALINEA></PARAG></ARTICLE><ARTICLE IDENTIFIER="007"><TI.ART>Article 7</TI.ART><STI.ART>Entrustment of tasks and delegation of responsibilities</STI.ART><PARAG IDENTIFIER="007.001"><NO.PARAG>1.</NO.PARAG><ALINEA>When developing the college supervisory examination programme pursuant to Article 16, and updating it where necessary, the consolidating supervisor and the members of the college shall consider the possibility of agreements on voluntary entrustment of tasks and delegation of responsibilities pursuant to Article 116(1)(b) of Directive 2013/36/EU, especially if such entrustment or delegation is expected to lead to more efficient and effective supervision, in particular by removing unnecessary duplication of supervisory requirements, including those in relation to information requests.</ALINEA></PARAG><PARAG IDENTIFIER="007.002"><NO.PARAG>2.</NO.PARAG><ALINEA>The conclusion of an agreement on entrustment of tasks or delegation of responsibilities shall be notified by the consolidating supervisor to the EU parent undertaking, and by the competent authority, which delegates its powers, to the institution concerned.</ALINEA></PARAG></ARTICLE><ARTICLE IDENTIFIER="008"><TI.ART>Article 8</TI.ART><STI.ART>Exchange of information between college members and a group of institutions</STI.ART><PARAG IDENTIFIER="008.001"><NO.PARAG>1.</NO.PARAG><ALINEA>The consolidating supervisor shall be responsible for communicating to and requesting information from the EU parent undertaking. The members of the college shall be responsible for communicating to and requesting information from the institutions and branches under their supervisory remit.</ALINEA></PARAG><PARAG IDENTIFIER="008.002"><NO.PARAG>2.</NO.PARAG><ALINEA>When, exceptionally, a member of the college intends to communicate to or request information from the EU parent undertaking, it shall inform in advance the consolidating supervisor.</ALINEA></PARAG><?PAGE NO="9"?><PARAG IDENTIFIER="008.003"><NO.PARAG>3.</NO.PARAG><ALINEA>When, exceptionally, the consolidating supervisor intends to communicate to or request information from an institution or a branch outside its supervisory remit, it shall inform in advance the member of the college responsible for supervising this institution or branch.</ALINEA></PARAG></ARTICLE></DIVISION><DIVISION><TITLE><TI><P><HT TYPE="ITALIC">SECTION 2</HT></P></TI><STI><P><HT TYPE="BOLD"><HT TYPE="ITALIC">Planning and coordination of supervisory activities in going concern situations</HT></HT></P></STI></TITLE><ARTICLE IDENTIFIER="009"><TI.ART>Article 9</TI.ART><STI.ART>General conditions with regard to exchange of information between the consolidating supervisor and college members</STI.ART><PARAG IDENTIFIER="009.001"><NO.PARAG>1.</NO.PARAG><ALINEA>The consolidating supervisor and the members of the college shall exchange all information necessary to facilitate the exercise of the tasks referred to in Articles 112 and 113 of Directive 2013/36/EU, subject to the confidentiality requirements laid down in Section II of Chapter 1 in Title VII of that Directive, and where applicable, Articles 54 and 58 of Directive 2004/39/EC of the European Parliament and of the Council<NOTE NOTE.ID="E0007" NUMBERING="ARAB" TYPE="FOOTNOTE"><P>Directive 2004/39/EC of the European Parliament and of the Council of <DATE ISO="20040421">21 April 2004</DATE> on markets in financial instruments amending Council Directives 85/611/EEC and 93/6/EEC and Directive 2000/12/EC of the European Parliament and of the Council and repealing Council Directive 93/22/EEC (<REF.DOC.OJ COLL="L" DATE.PUB="20040430" NO.OJ="145" PAGE.FIRST="1">OJ L 145, 30.4.2004, p. 1</REF.DOC.OJ>).</P></NOTE>.</ALINEA></PARAG><PARAG IDENTIFIER="009.002"><NO.PARAG>2.</NO.PARAG><ALINEA>The consolidating supervisor and the members of the college shall also exchange all information necessary to facilitate the exercise of the tasks referred to in Article 8 of Directive 2014/59/EU.</ALINEA></PARAG><PARAG IDENTIFIER="009.003"><NO.PARAG>3.</NO.PARAG><ALINEA>The consolidating supervisor and the members of the college shall exchange the information referred to in paragraphs 1 and 2, whether received from a group entity, a competent or supervisory authority or any other source, and in accordance with Article 7 of the Implementing Regulation (EU) 2016/99. That information shall be sufficiently adequate, accurate and timely.</ALINEA></PARAG></ARTICLE><ARTICLE IDENTIFIER="010"><TI.ART>Article 10</TI.ART><STI.ART>Information exchange for performing group risk assessments and reaching joint decisions</STI.ART><PARAG IDENTIFIER="010.001"><NO.PARAG>1.</NO.PARAG><ALINEA>For the purposes of joint decisions on institution-specific prudential requirements as referred to in Article 113 of Directive 2013/36/EU, the consolidating supervisor and the relevant members of the college referred to in paragraph 1 of that Article shall exchange all information necessary, at both individual and consolidated level, to reach a joint decision.</ALINEA></PARAG><PARAG IDENTIFIER="010.002"><NO.PARAG>2.</NO.PARAG><ALINEA><P>In particular, the consolidating supervisor and the relevant members of the college referred to in paragraph 1 shall exchange information on the outcomes of the supervisory review and evaluation process performed in accordance to Article 97 of Directive 2013/36/EU. This information shall provide the outcome of the assessment, at least, of the following elements:</P><LIST TYPE="alpha"><ITEM><NP><NO.P>(a)</NO.P><TXT>business model analysis, including the assessment of the viability of current business model and sustainability of institution's forward-looking business strategy;</TXT></NP></ITEM><ITEM><NP><NO.P>(b)</NO.P><TXT>internal governance arrangements and institution-wide controls;</TXT></NP></ITEM><ITEM><NP><NO.P>(c)</NO.P><TXT>individual risks to institution's capital, covering the following elements:</TXT><P><LIST TYPE="roman"><ITEM><NP><NO.P>(i)</NO.P><TXT>inherent individual risks;</TXT></NP></ITEM><ITEM><NP><NO.P>(ii)</NO.P><TXT>risk management and controls;</TXT></NP></ITEM></LIST></P></NP></ITEM><ITEM><NP><NO.P>(d)</NO.P><TXT>capital adequacy assessment, including proposed required own funds pursuant to Article 104(1)(a) of Directive 2013/36/EU;</TXT></NP></ITEM><?PAGE NO="10"?><ITEM><NP><NO.P>(e)</NO.P><TXT>risks to institution's liquidity and funding, covering the following elements:</TXT><P><LIST TYPE="roman"><ITEM><NP><NO.P>(i)</NO.P><TXT>liquidity risk and funding risk;</TXT></NP></ITEM><ITEM><NP><NO.P>(ii)</NO.P><TXT>liquidity and funding risk management;</TXT></NP></ITEM></LIST></P></NP></ITEM><ITEM><NP><NO.P>(f)</NO.P><TXT>liquidity adequacy assessment, including proposed quantitative and qualitative liquidity measures pursuant to Article 105 of Directive 2013/36/EU;</TXT></NP></ITEM><ITEM><NP><NO.P>(g)</NO.P><TXT>other supervisory measures or early intervention measures taken or planned to be taken in order to address the inefficiencies identified as a result of the supervisory review and evaluation process;</TXT></NP></ITEM><ITEM><NP><NO.P>(h)</NO.P><TXT>results of the supervisory stress tests performed pursuant to Article 100 of Directive 2013/36/EU;</TXT></NP></ITEM><ITEM><NP><NO.P>(i)</NO.P><TXT>findings from on-site inspections and off-site monitoring that are relevant for the assessment of the risk profile of the group or any of its entities.</TXT></NP></ITEM></LIST></ALINEA></PARAG></ARTICLE><ARTICLE IDENTIFIER="011"><TI.ART>Article 11</TI.ART><STI.ART>Information exchange with regard to the ongoing review of the permission to use internal approaches and non-material extensions or changes in internal models</STI.ART><PARAG IDENTIFIER="011.001"><NO.PARAG>1.</NO.PARAG><ALINEA>For the purposes of ensuring coherence and coordination with regard to the ongoing review of the permission to use internal approaches as referred to in Article 101 of Directive 2013/36/EU, the consolidating supervisor and the relevant members of the college, who supervise institutions that have been granted permission to use internal approaches in accordance with Articles 143(1), Article 151(4) or (9), Article 283, Article 312(2), or Article 363 of Regulation (EU) No 575/2013, shall exchange all information on the outcome of this ongoing review and all other relevant information.</ALINEA></PARAG><PARAG IDENTIFIER="011.002"><NO.PARAG>2.</NO.PARAG><ALINEA><P>Where the consolidating supervisor or any relevant member of the college referred to in paragraph 1 has identified that an institution authorised in a Member State, including the EU parent undertaking, no longer meets all requirements for applying an internal approach or has identified weaknesses in accordance with Article 101 of Directive 2013/36/EU, they shall immediately exchange the following information, as applicable, for the purposes of facilitating the reach of common agreement as referred to in Article 8 of Implementing Regulation (EU) 2016/99:</P><LIST TYPE="alpha"><ITEM><NP><NO.P>(a)</NO.P><TXT>assessment of the effect of the weaknesses identified and issues of non-compliance and their materiality;</TXT></NP></ITEM><ITEM><NP><NO.P>(b)</NO.P><TXT>assessment of the plan to restore compliance and to address the weaknesses identified as presented by the EU parent institution or any institution authorised in a Member State, including information on the timeline for its implementation;</TXT></NP></ITEM><ITEM><NP><NO.P>(c)</NO.P><TXT>information on the intention of the consolidating supervisor or of any relevant member of the college to revoke the permission or restrict the use of the model to compliant areas or those where compliance can be achieved within an appropriate timeline, or those areas that are not affected by the weaknesses identified;</TXT></NP></ITEM><ITEM><NP><NO.P>(d)</NO.P><TXT>information on any proposed additional own funds requirements pursuant to Article 104(2)(d) of Directive 2013/36/EU as a supervisory measure to address the issues of non-compliance or weaknesses identified.</TXT></NP></ITEM></LIST></ALINEA></PARAG><PARAG IDENTIFIER="011.003"><NO.PARAG>3.</NO.PARAG><ALINEA>The consolidating supervisor and the relevant members of the college referred to in paragraph 1 shall also exchange information regarding extensions or changes in these internal models which are not material model extensions or changes, as referred to in Article 13 of Commission Implementing Regulation (EU) 2016/100<NOTE NOTE.ID="E0008" NUMBERING="ARAB" TYPE="FOOTNOTE"><P>Commission Implementing Regulation (EU) 2016/100 of <DATE ISO="20151016">16 October 2015</DATE> laying down implementing technical standards specifying the joint decision process with regard to the application for certain prudential permissions pursuant to Regulation (EU) No 575/2013 of the European Parliament and of the Council (see page 45 of this Official Journal).</P></NOTE>.</ALINEA></PARAG><PARAG IDENTIFIER="011.004"><NO.PARAG>4.</NO.PARAG><ALINEA>Information referred to in paragraphs 1 and 2 shall be discussed and taken into account while developing the group risk assessment and reaching a joint decision in accordance with Article 113(1)(a) of Directive 2013/36/EU.</ALINEA></PARAG></ARTICLE><?PAGE NO="11"?><ARTICLE IDENTIFIER="012"><TI.ART>Article 12</TI.ART><STI.ART>Information exchange on early warning signs, potential risks and vulnerabilities</STI.ART><PARAG IDENTIFIER="012.001"><NO.PARAG>1.</NO.PARAG><ALINEA>The consolidating supervisor and the members of the college participating in the development of a group risk assessment report referred to in Article 113(2)(a) of Directive 2013/36/EU or a group liquidity risk assessment report referred to in Article 113(2)(b) of that Directive for the purposes of reaching joint decisions on institution-specific prudential requirements in accordance with that Article shall exchange quantitative information aiming to identify early warning signs, potential risks and vulnerabilities and to inform the group risk assessment report and group liquidity risk assessment report.</ALINEA></PARAG><PARAG IDENTIFIER="012.002"><NO.PARAG>2.</NO.PARAG><ALINEA><P>The information referred to in paragraph 1 shall be developed based on the information collected by the competent authorities in accordance with Implementing Regulation (EU) No 680/2014, in order to ensure consistency and comparability on the data used. This information shall cover at least all group entities authorised or established in a Member State, and at least the following areas:</P><LIST TYPE="alpha"><ITEM><NP><NO.P>(a)</NO.P><TXT>capital;</TXT></NP></ITEM><ITEM><NP><NO.P>(b)</NO.P><TXT>liquidity;</TXT></NP></ITEM><ITEM><NP><NO.P>(c)</NO.P><TXT>asset quality;</TXT></NP></ITEM><ITEM><NP><NO.P>(d)</NO.P><TXT>funding;</TXT></NP></ITEM><ITEM><NP><NO.P>(e)</NO.P><TXT>profitability;</TXT></NP></ITEM><ITEM><NP><NO.P>(f)</NO.P><TXT>concentration risk.</TXT></NP></ITEM></LIST></ALINEA></PARAG><PARAG IDENTIFIER="012.003"><NO.PARAG>3.</NO.PARAG><ALINEA>The consolidating supervisor and the members of the college referred to in paragraph 1 shall also consider exchanging information on the macroeconomic environment in which the group of institutions and its group entities operate.</ALINEA></PARAG></ARTICLE><ARTICLE IDENTIFIER="013"><TI.ART>Article 13</TI.ART><STI.ART>Information exchange with regard to non-compliance and sanctions</STI.ART><PARAG IDENTIFIER="013.001"><NO.PARAG>1.</NO.PARAG><ALINEA>The members of the college shall communicate to the consolidating supervisor information regarding any situations in respect of which the members of the college have determined that an institution or a branch under their supervisory remit has not complied with national or Union law or with requirements, in relation to the prudential supervision or market conduct supervision of institutions, including the requirements laid down in Regulation (EU) No 575/2013 and Directive 2013/36/EU and any of the administrative penalties imposed or other administrative measures applied in accordance with Articles 64 to 67 of Directive 2013/36/EU when this information affects or is likely to affect the risk profile of the group or any of its group entities. The members of the college shall discuss with the consolidating supervisor the possible impact of these issues of non-compliance and sanctions for the group entities or for the group as a whole.</ALINEA></PARAG><PARAG IDENTIFIER="013.002"><NO.PARAG>2.</NO.PARAG><ALINEA>The consolidating supervisor shall decide to communicate information specified in paragraph 1 to the members of the college for whom this information is deemed relevant in accordance with Article 7 of Implementing Regulation (EU) 2016/99.</ALINEA></PARAG></ARTICLE><ARTICLE IDENTIFIER="014"><TI.ART>Article 14</TI.ART><STI.ART>Information exchange for the assessment of the group recovery plan</STI.ART><PARAG IDENTIFIER="014.001"><NO.PARAG>1.</NO.PARAG><ALINEA>The consolidating supervisor and the members of the college shall exchange all information necessary for those who participate in the process of joint decision on the elements referred to in Article 8(2) of Directive 2014/59/EU.</ALINEA></PARAG><PARAG IDENTIFIER="014.002"><NO.PARAG>2.</NO.PARAG><ALINEA>For the purposes of paragraph 1, the consolidating supervisor shall provide the group recovery plan to the members of the college following the procedure specified in Article 7 of Implementing Regulation (EU) 2016/99.</ALINEA></PARAG><?PAGE NO="12"?><PARAG IDENTIFIER="014.003"><NO.PARAG>3.</NO.PARAG><ALINEA>The consolidating supervisor shall ensure that all members of the college are appropriately informed of the outcome of the process referred to in paragraph 1.</ALINEA></PARAG><PARAG IDENTIFIER="014.004"><NO.PARAG>4.</NO.PARAG><ALINEA>The consolidating supervisor shall inform the group-level resolution authority about the timeline followed for the review and assessment of the group recovery plan and indicate a date for the group-level resolution authority to provide its recommendations, if any, in accordance to Article 6(4) of Directive 2014/59/EU.</ALINEA></PARAG></ARTICLE><ARTICLE IDENTIFIER="015"><TI.ART>Article 15</TI.ART><STI.ART>Information exchange with regard to group financial support agreements</STI.ART><ALINEA>The consolidating supervisor shall ensure that all members of the college are appropriately informed of the main terms of authorisations of group financial support agreements that have been granted in accordance with the joint decision process referred to in Article 20 of Directive 2014/59/EU.</ALINEA></ARTICLE><ARTICLE IDENTIFIER="016"><TI.ART>Article 16</TI.ART><STI.ART>Establishment and update of the college supervisory examination programme</STI.ART><PARAG IDENTIFIER="016.001"><NO.PARAG>1.</NO.PARAG><ALINEA>For the purposes of establishing the college supervisory examination programme in accordance with Article 116(1)(c) of Directive 2013/36/EU, the consolidating supervisor and the members of the college shall identify the supervisory activities to be undertaken.</ALINEA></PARAG><PARAG IDENTIFIER="016.002"><NO.PARAG>2.</NO.PARAG><ALINEA><P>The college supervisory examination programme shall contain at least the following:</P><LIST TYPE="alpha"><ITEM><NP><NO.P>(a)</NO.P><TXT>the areas of joint work identified as a result of the group risk assessment and group liquidity risk assessment and joint decisions on institution-specific prudential requirements pursuant to Article 113 of Directive 2013/36/EU or as a result of any other college activities undertaken, including efforts to contribute to efficient supervision and to remove unnecessary duplication of tasks in accordance with Article 116(1)(d) of that Directive;</TXT></NP></ITEM><ITEM><NP><NO.P>(b)</NO.P><TXT>the respective supervisory examination programmes of the consolidating supervisor and the members of the college for the parent undertaking and for all institutions authorised and branches established in a Member State;</TXT></NP></ITEM><ITEM><NP><NO.P>(c)</NO.P><TXT>the areas of focus of the college work and its planned supervisory activities, including planned onsite inspections pursuant to Article 99(1)(c) of Directive 2013/36/EU;</TXT></NP></ITEM><ITEM><NP><NO.P>(d)</NO.P><TXT>the members of the college responsible for undertaking the planned supervisory activities;</TXT></NP></ITEM><ITEM><NP><NO.P>(e)</NO.P><TXT>the expected timelines, both in terms of timing and duration, for each of the planned supervisory activities.</TXT></NP></ITEM></LIST></ALINEA></PARAG><PARAG IDENTIFIER="016.003"><NO.PARAG>3.</NO.PARAG><ALINEA>The establishment and update of the college supervisory examination programme shall be performed pursuant to Article 11 of Implementing Regulation (EU) 2016/99.</ALINEA></PARAG></ARTICLE></DIVISION><DIVISION><TITLE><TI><P><HT TYPE="ITALIC">SECTION 3</HT></P></TI><STI><P><HT TYPE="BOLD"><HT TYPE="ITALIC">Planning and coordination of supervisory activities in preparation for and during emergency situations</HT></HT></P></STI></TITLE><ARTICLE IDENTIFIER="017"><TI.ART>Article 17</TI.ART><STI.ART>Establishment of a college framework for emergency situations</STI.ART><PARAG IDENTIFIER="017.001"><NO.PARAG>1.</NO.PARAG><ALINEA>The consolidating supervisor and the members of the college shall establish a college framework in anticipation of possible emergency situations in accordance with Article 112(1)(c) of Directive 2013/36/EU (hereinafter <QUOT.START CODE="2018" ID="QS0002" REF.END="QE0002"/>college framework for emergency situations<QUOT.END CODE="2019" ID="QE0002" REF.START="QS0002"/>), taking into account the specificities and structure of the group of institutions.</ALINEA></PARAG><PARAG IDENTIFIER="017.002"><NO.PARAG>2.</NO.PARAG><ALINEA><P>The college framework for emergency situations shall include at least the following:</P><LIST TYPE="alpha"><ITEM><NP><NO.P>(a)</NO.P><TXT>the college-specific procedures that shall apply where an emergency situation as referred to in Article 114(1) of Directive 2013/36/EU arises;</TXT></NP></ITEM><?PAGE NO="13"?><ITEM><NP><NO.P>(b)</NO.P><TXT>the minimum set of information that shall be exchanged where an emergency situation as referred to in Article 114(1) of Directive 2013/36/EU arises.</TXT></NP></ITEM></LIST></ALINEA></PARAG><PARAG IDENTIFIER="017.003"><NO.PARAG>3.</NO.PARAG><ALINEA><P>The minimum set of information referred to in point (b) of paragraph 2 shall include the following:</P><LIST TYPE="alpha"><ITEM><NP><NO.P>(a)</NO.P><TXT>an outline of the situation that has occurred, including the underlying cause of the emergency situation, and the expected impact of the emergency situation on the group entities and the group as a whole, on the market liquidity and on the stability of the financial system;</TXT></NP></ITEM><ITEM><NP><NO.P>(b)</NO.P><TXT>an explanation of the measures and actions that have been taken or are planned to be taken, by the consolidation supervisor or any of the members of the college or by the group entities themselves;</TXT></NP></ITEM><ITEM><NP><NO.P>(c)</NO.P><TXT>the latest available quantitative information regarding liquidity and capital position of the group entities affected or likely to be affected by the emergency situation on an individual and consolidated basis.</TXT></NP></ITEM></LIST></ALINEA></PARAG></ARTICLE><ARTICLE IDENTIFIER="018"><TI.ART>Article 18</TI.ART><STI.ART>General conditions with regard to exchange of information during an emergency situation</STI.ART><PARAG IDENTIFIER="018.001"><NO.PARAG>1.</NO.PARAG><ALINEA>The consolidating supervisor and the members of the college shall exchange all information necessary to facilitate the exercise of the tasks referred to in Article 114(1) of Directive 2013/36/EU, subject to the confidentiality requirements laid down in Section II of Chapter 1 of Title VII of that Directive, and where applicable, Articles 54 and 58 of Directive 2004/39/EC.</ALINEA></PARAG><PARAG IDENTIFIER="018.002"><NO.PARAG>2.</NO.PARAG><ALINEA>Upon being alerted of an emergency situation by any member or observer of the college or having identified an emergency situation, the consolidating supervisor shall communicate the information referred to in Article 17(2)(b), following the procedures referred to in Article 17(2)(a), to the members of the college who supervise group entities that are affected or likely to be affected by the emergency situation, and the EBA.</ALINEA></PARAG><PARAG IDENTIFIER="018.003"><NO.PARAG>3.</NO.PARAG><ALINEA>Depending on the nature, severity, potential systemic impact or other impact, and likelihood of contagion of the emergency situation, the members of the college who supervise group entities that are affected or likely to be affected by the emergency situation and the consolidating supervisor may decide to exchange additional information.</ALINEA></PARAG><PARAG IDENTIFIER="018.004"><NO.PARAG>4.</NO.PARAG><ALINEA>The consolidating supervisor shall consider whether the information referred to in paragraphs 2 and 3 is relevant for the performance of the tasks of the resolution college. In this case, the consolidating supervisor shall communicate this information to the group-level resolution authority as defined in point 44 of Article 2(1) of Directive 2014/59/EU.</ALINEA></PARAG><PARAG IDENTIFIER="018.005"><NO.PARAG>5.</NO.PARAG><ALINEA>The information referred to in paragraphs 2 and 3, where applicable, shall be updated immediately when new information is available.</ALINEA></PARAG><PARAG IDENTIFIER="018.006"><NO.PARAG>6.</NO.PARAG><ALINEA>When the exchange of information or communication referred to in this Article is made orally, the concerned competent authorities shall follow up it with written communication in a timely manner.</ALINEA></PARAG></ARTICLE><ARTICLE IDENTIFIER="019"><TI.ART>Article 19</TI.ART><STI.ART>Coordination of the supervisory assessment of an emergency situation</STI.ART><PARAG IDENTIFIER="019.001"><NO.PARAG>1.</NO.PARAG><ALINEA>Where an emergency situation occurs, the consolidating supervisor shall coordinate the assessment of the emergency situation (hereinafter <QUOT.START CODE="2018" ID="QS0003" REF.END="QE0003"/>coordinated supervisory assessment<QUOT.END CODE="2019" ID="QE0003" REF.START="QS0003"/>) in cooperation with the members of the college who supervise group entities that are affected or likely to be affected by that emergency situation.</ALINEA></PARAG><PARAG IDENTIFIER="019.002"><NO.PARAG>2.</NO.PARAG><ALINEA><P>The coordinated supervisory assessment of the emergency situation, performed in accordance with Article 14 of Implementing Regulation (EU) 2016/99, shall cover at least the following elements:</P><LIST TYPE="alpha"><ITEM><NP><NO.P>(a)</NO.P><TXT>the nature and severity of the emergency situation;</TXT></NP></ITEM><?PAGE NO="14"?><ITEM><NP><NO.P>(b)</NO.P><TXT>the impact or potential impact of the emergency situation on the group and on any of its affected or likely to be affected group entities;</TXT></NP></ITEM><ITEM><NP><NO.P>(c)</NO.P><TXT>the risk of cross-border contagion.</TXT></NP></ITEM></LIST></ALINEA></PARAG><PARAG IDENTIFIER="019.003"><NO.PARAG>3.</NO.PARAG><ALINEA>When assessing point (c) of paragraph 2, the consolidating supervisor shall consider the potential systemic consequences in any of the Members States where entities of the group are authorised or where significant branches are established.</ALINEA></PARAG></ARTICLE><ARTICLE IDENTIFIER="020"><TI.ART>Article 20</TI.ART><STI.ART>Coordination of the supervisory response to an emergency situation</STI.ART><PARAG IDENTIFIER="020.001"><NO.PARAG>1.</NO.PARAG><ALINEA>Where an emergency situation occurs, the consolidating supervisor shall coordinate the development of a supervisory response to the emergency situation (hereinafter <QUOT.START CODE="2018" ID="QS0004" REF.END="QE0004"/>coordinated supervisory response<QUOT.END CODE="2019" ID="QE0004" REF.START="QS0004"/> in cooperation with the members of the college who supervise group entities that are affected or likely to be affected by that emergency situation.</ALINEA></PARAG><PARAG IDENTIFIER="020.002"><NO.PARAG>2.</NO.PARAG><ALINEA>The coordinated supervisory assessment referred to in Article 19 shall form the basis of the coordinated supervisory response, which shall define the supervisory actions needed, their scope, and the timetable for their implementation.</ALINEA></PARAG><PARAG IDENTIFIER="020.003"><NO.PARAG>3.</NO.PARAG><ALINEA>The coordinated supervisory response shall be developed by the consolidating supervisor and the members of the college who supervise group entities that are affected or likely to be affected by the emergency situation.</ALINEA></PARAG></ARTICLE><ARTICLE IDENTIFIER="021"><TI.ART>Article 21</TI.ART><STI.ART>Monitoring of the implementation of the coordinated supervisory response to an emergency situation</STI.ART><PARAG IDENTIFIER="021.001"><NO.PARAG>1.</NO.PARAG><ALINEA>The consolidating supervisor and the members of the college who supervise group entities that are affected or likely to be affected by the emergency situation shall monitor and exchange information on the implementation of the coordinated supervisory response referred to in Article 20.</ALINEA></PARAG><PARAG IDENTIFIER="021.002"><NO.PARAG>2.</NO.PARAG><ALINEA>The information to be exchanged shall include at least an update on the implementation of the agreed actions within the foreseen timeline, as referred to in Article 20(2), and the need to update or adjust these actions.</ALINEA></PARAG></ARTICLE><ARTICLE IDENTIFIER="022"><TI.ART>Article 22</TI.ART><STI.ART>Coordination of external communication in an emergency situation</STI.ART><PARAG IDENTIFIER="022.001"><NO.PARAG>1.</NO.PARAG><ALINEA>Within the framework of applicable Union and national law, the consolidating supervisor and the members of the college who supervise group entities that are affected or likely to be affected by the emergency situation shall coordinate to the extent possible their external communications.</ALINEA></PARAG><PARAG IDENTIFIER="022.002"><NO.PARAG>2.</NO.PARAG><ALINEA><P>For the purpose of coordinating external communication, the consolidating supervisor and the members of the college shall agree on the following elements:</P><LIST TYPE="alpha"><ITEM><NP><NO.P>(a)</NO.P><TXT>the allocation of responsibilities for coordinating external communication at the different stages of the emergency situation;</TXT></NP></ITEM><ITEM><NP><NO.P>(b)</NO.P><TXT>the level of information to be disclosed taking into account the need to maintain market confidence and any other additional disclosure obligations where financial instruments issued by group entities affected or likely to be affected by the emergency situation are publicly traded in one or more regulated markets in the Union;</TXT></NP></ITEM><ITEM><NP><NO.P>(c)</NO.P><TXT>the coordination of public statements, including those made by only one member of the college, in particular where these are likely to have consequences for group entities supervised by other members of the college;</TXT></NP></ITEM><?PAGE NO="15"?><ITEM><NP><NO.P>(d)</NO.P><TXT>the allocation of responsibilities and appropriate timing for contacting group entities;</TXT></NP></ITEM><ITEM><NP><NO.P>(e)</NO.P><TXT>the allocation of responsibilities and actions to be taken for communicating externally the coordinated actions taken to address the emergency situation;</TXT></NP></ITEM><ITEM><NP><NO.P>(f)</NO.P><TXT>a description of possible coordination with another group or college that may be involved in dealing with an emergency situation affecting the group, such as a crisis management group or a resolution college.</TXT></NP></ITEM></LIST></ALINEA></PARAG></ARTICLE></DIVISION></DIVISION><DIVISION><TITLE><TI><P>CHAPTER 3</P></TI><STI><P><HT TYPE="BOLD">CONDITIONS REGARDING THE FUNCTIONING OF COLLEGES FORMED IN ACCORDANCE WITH ARTICLE 51(3) OF DIRECTIVE 2013/36/EU</HT></P></STI></TITLE><DIVISION><TITLE><TI><P><HT TYPE="ITALIC">SECTION 1</HT></P></TI><STI><P><HT TYPE="BOLD"><HT TYPE="ITALIC">Establishment and functioning of colleges</HT></HT></P></STI></TITLE><ARTICLE IDENTIFIER="023"><TI.ART>Article 23</TI.ART><STI.ART>Designation of the members and observers of a college</STI.ART><PARAG IDENTIFIER="023.001"><NO.PARAG>1.</NO.PARAG><ALINEA><P>Following the performance of the mapping of the institution with branches in other Member States pursuant to Article 2 of Implementing Regulation (EU) 2016/99, the competent authorities of the home Member State shall invite the following authorities to become members of the college:</P><LIST TYPE="alpha"><ITEM><NP><NO.P>(a)</NO.P><TXT>the competent authorities of the host Member States where significant branches are established;</TXT></NP></ITEM><ITEM><NP><NO.P>(b)</NO.P><TXT>the ESCB central banks of Member States that are involved in accordance with their national law in the prudential supervision of the significant branches referred to in point a, but which are not competent authorities;</TXT></NP></ITEM><ITEM><NP><NO.P>(c)</NO.P><TXT>the EBA.</TXT></NP></ITEM></LIST></ALINEA></PARAG><PARAG IDENTIFIER="023.002"><NO.PARAG>2.</NO.PARAG><ALINEA>The competent authorities of the home Member State may invite the competent authorities of host Member States where non-significant branches are established to participate in the college as observers in accordance with the process determined in Article 3(1)(b) of Implementing Regulation (EU) 2016/99.</ALINEA></PARAG><PARAG IDENTIFIER="023.003"><NO.PARAG>3.</NO.PARAG><ALINEA>The competent authorities of the home Member State may invite the supervisory authorities of third countries where branches of the relevant institution are established to participate in the college as observers in accordance with the process determined in Article 3(1)(c) of Implementing Regulation (EU) 2016/99.</ALINEA></PARAG><PARAG IDENTIFIER="023.004"><NO.PARAG>4.</NO.PARAG><ALINEA><P>The competent authorities of the home Member State may invite the following authorities to participate in the college as observers in accordance with the process determined in Article 3(1)(d) of Implementing Regulation (EU) 2016/99:</P><LIST TYPE="alpha"><ITEM><NP><NO.P>(a)</NO.P><TXT>the ESCB central banks which are not empowered by national law to supervise the institution or its branches established in a Member State;</TXT></NP></ITEM><ITEM><NP><NO.P>(b)</NO.P><TXT>the public authorities or bodies in a Member State which are responsible for or involved in the supervision of the institution or its branches, including competent authorities responsible for the supervision of markets in financial instruments, the prevention of the use of the financial system for the purpose of money laundering and terrorist financing, or consumer protection.</TXT></NP></ITEM></LIST></ALINEA></PARAG><PARAG IDENTIFIER="023.005"><NO.PARAG>5.</NO.PARAG><ALINEA>The competent authorities of the home Member State and the members of the college shall specify the arrangements covering the participation of the observers in the college in the written arrangements referred to in Article 51(3) of Directive 2013/36/EU. The competent authorities of the home Member State shall notify these arrangements to the observers.</ALINEA></PARAG></ARTICLE><?PAGE NO="16"?><ARTICLE IDENTIFIER="024"><TI.ART>Article 24</TI.ART><STI.ART>Communication of the setting up and composition of a college</STI.ART><ALINEA>The competent authorities of the home Member State shall communicate to the institution the establishment of a college and the identity of its members and observers, as well as any changes in that composition.</ALINEA></ARTICLE><ARTICLE IDENTIFIER="025"><TI.ART>Article 25</TI.ART><STI.ART>Establishment of the written coordination and cooperation arrangements</STI.ART><ALINEA>The establishment and functioning of colleges for significant branches formed in accordance with Article 51(3) of Directive 2013/36/EU shall be based on written coordination and cooperation arrangements to be determined in accordance with Article 5 of this Regulation.</ALINEA></ARTICLE><ARTICLE IDENTIFIER="026"><TI.ART>Article 26</TI.ART><STI.ART>Participation in college meetings and activities</STI.ART><PARAG IDENTIFIER="026.001"><NO.PARAG>1.</NO.PARAG><ALINEA><P>When deciding which authorities shall participate in a college meeting or activity in accordance with Article 51(3) of Directive 2013/36/EU, the competent authorities of the home Member State shall take into account the following:</P><LIST TYPE="alpha"><ITEM><NP><NO.P>(a)</NO.P><TXT>the topics to be discussed and the objective of the meeting or activity, in particular with regards to their relevance for each branch;</TXT></NP></ITEM><ITEM><NP><NO.P>(b)</NO.P><TXT>the importance of the branch in the Member State where it is established and its importance for the institution.</TXT></NP></ITEM></LIST></ALINEA></PARAG><PARAG IDENTIFIER="026.002"><NO.PARAG>2.</NO.PARAG><ALINEA>The competent authorities of the home Member State and the members of the college shall ensure that the most appropriate representatives participate in the college meetings or activities, based on the topics discussed and objectives pursued. Those representatives shall have the power to commit their authorities as members of the college, to the maximum extent possible, for the decisions planned to be taken during the meetings or activities.</ALINEA></PARAG><PARAG IDENTIFIER="026.003"><NO.PARAG>3.</NO.PARAG><ALINEA>The competent authorities of the home Member State may invite representatives of the institution to participate in a college meeting or activity, based on the topics and objectives of the college meeting or activity.</ALINEA></PARAG></ARTICLE><ARTICLE IDENTIFIER="027"><TI.ART>Article 27</TI.ART><STI.ART>Conditions for communication</STI.ART><PARAG IDENTIFIER="027.001"><NO.PARAG>1.</NO.PARAG><ALINEA>The communication with the institution and its branches shall be organised according to the supervisory responsibilities given to the competent authorities of the home Member State and the members of the college by Chapter 4 of Title V and Title VII of Directive 2013/36/EU.</ALINEA></PARAG><PARAG IDENTIFIER="027.002"><NO.PARAG>2.</NO.PARAG><ALINEA>The college meetings and activities shall be organised in accordance with Article 18 of Implementing Regulation (EU) 2016/99.</ALINEA></PARAG></ARTICLE></DIVISION><DIVISION><TITLE><TI><P><HT TYPE="ITALIC">SECTION 2</HT></P></TI><STI><P><HT TYPE="BOLD"><HT TYPE="ITALIC">Planning and coordination of supervisory activities in going concern situations</HT></HT></P></STI></TITLE><ARTICLE IDENTIFIER="028"><TI.ART>Article 28</TI.ART><STI.ART>General conditions with regard to exchange of information between the competent authorities of the home Member State and college members</STI.ART><PARAG IDENTIFIER="028.001"><NO.PARAG>1.</NO.PARAG><ALINEA>The competent authorities of the home Member State and the members of the college shall exchange all information necessary to facilitate the cooperation under Article 50 and Article 51(2) of Directive 2013/36/EU.</ALINEA></PARAG><?PAGE NO="17"?><PARAG IDENTIFIER="028.002"><NO.PARAG>2.</NO.PARAG><ALINEA>The competent authorities of the home Member State and the members of the college shall also exchange all information necessary to facilitate the cooperation referred to in Articles 6, 7 and 8 of Directive 2014/59/EU.</ALINEA></PARAG><PARAG IDENTIFIER="028.003"><NO.PARAG>3.</NO.PARAG><ALINEA>The competent authorities of the home Member State and the members of the college shall exchange the information referred to in paragraphs 1 and 2, whether received from the institution, a competent or supervisory authority or any other source. This information shall be sufficiently adequate, accurate and timely.</ALINEA></PARAG></ARTICLE><ARTICLE IDENTIFIER="029"><TI.ART>Article 29</TI.ART><STI.ART>Information exchange for the outcome of the supervisory review and evaluation process</STI.ART><ALINEA>The information to be communicated by the competent authorities of the home Member State to the members of the college shall cover the information referred to in Article 4, Article 5, Articles 7 to 13 and Article 17 of Commission Delegated Regulation (EU) No 524/2014<NOTE NOTE.ID="E0009" NUMBERING="ARAB" TYPE="FOOTNOTE"><P>Commission Delegated Regulation (EU) No 524/2014 of <DATE ISO="20140312">12 March 2014</DATE> supplementing Directive 2013/36/EU of the European Parliament and of the Council with regard to regulatory technical standards specifying the information that competent authorities of home and host Member States supply to one another (<REF.DOC.OJ COLL="L" DATE.PUB="20140520" NO.OJ="148" PAGE.FIRST="6">OJ L 148, 20.5.2014, p. 6</REF.DOC.OJ>).</P></NOTE> as a result of the supervisory review and evaluation process performed in accordance with Article 97 of Directive 2013/36/EU.</ALINEA></ARTICLE><ARTICLE IDENTIFIER="030"><TI.ART>Article 30</TI.ART><STI.ART>Information exchange for the assessment of the recovery plan</STI.ART><PARAG IDENTIFIER="030.001"><NO.PARAG>1.</NO.PARAG><ALINEA>The competent authorities of the home Member State shall consult the competent authorities of the host Member States where significant branches are established on the recovery plan in so far as is relevant to that branch, in accordance with Article 6(2) of Directive 2014/59/EU.</ALINEA></PARAG><PARAG IDENTIFIER="030.002"><NO.PARAG>2.</NO.PARAG><ALINEA>For the purposes of paragraph 1, the competent authorities of the home Member State shall provide the recovery plan of the institution to the competent authorities of the host Member States where significant branches are established in accordance with Article 19 of Implementing Regulation (EU) 2016/99.</ALINEA></PARAG><PARAG IDENTIFIER="030.003"><NO.PARAG>3.</NO.PARAG><ALINEA>The competent authorities of the home Member State shall ensure that all members of the college are appropriately informed of the outcome of the process referred to in paragraph 1.</ALINEA></PARAG></ARTICLE><ARTICLE IDENTIFIER="031"><TI.ART>Article 31</TI.ART><STI.ART>Establishment and update of the college supervisory examination programme</STI.ART><PARAG IDENTIFIER="031.001"><NO.PARAG>1.</NO.PARAG><ALINEA>For the purposes of establishing the college supervisory examination programme referred to in Article 99 of Directive 2013/36/EU, the competent authorities of the home Member State and the members of the college shall identify the supervisory activities to be undertaken.</ALINEA></PARAG><PARAG IDENTIFIER="031.002"><NO.PARAG>2.</NO.PARAG><ALINEA><P>The college supervisory examination programme shall contain at least the following:</P><LIST TYPE="alpha"><ITEM><NP><NO.P>(a)</NO.P><TXT>the areas of joint work identified as a result of the supervisory review and evaluation process pursuant to Article 97 of Directive 2013/36/EU or as a result of any other college activities undertaken;</TXT></NP></ITEM><ITEM><NP><NO.P>(b)</NO.P><TXT>the areas of focus of the college work and its planned supervisory activities, including planned on-the-spot checks and inspections of the significant branches pursuant to Article 52(3) of Directive 2013/36/EU;</TXT></NP></ITEM><ITEM><NP><NO.P>(c)</NO.P><TXT>the members of the college responsible for undertaking the planned supervisory activities;</TXT></NP></ITEM><ITEM><NP><NO.P>(d)</NO.P><TXT>the expected timelines, both in terms of timing and duration, for each of the planned supervisory activities.</TXT></NP></ITEM></LIST></ALINEA></PARAG><?PAGE NO="18"?><PARAG IDENTIFIER="031.003"><NO.PARAG>3.</NO.PARAG><ALINEA>When developing the college supervisory examination programme, and updating it where necessary, the competent authorities of the home Member State and the members of the college shall consider the possibility of agreements on voluntary entrustment of tasks and delegation of responsibilities, especially if such entrustment or delegation is expected to lead to more efficient and effective supervision, in particular by removing unnecessary duplication of supervisory requirements, including those in relation to information requests.</ALINEA></PARAG><PARAG IDENTIFIER="031.004"><NO.PARAG>4.</NO.PARAG><ALINEA>The conclusion of an agreement on entrustment of tasks or delegation of responsibilities shall be notified by the competent authorities of the home Member State to the institution concerned, and by the competent authority, which delegates its powers, to the branch concerned.</ALINEA></PARAG><PARAG IDENTIFIER="031.005"><NO.PARAG>5.</NO.PARAG><ALINEA>The establishment and update of the college supervisory examination programme shall be performed pursuant to Article 20 of Implementing Regulation (EU) 2016/99.</ALINEA></PARAG></ARTICLE></DIVISION><DIVISION><TITLE><TI><P><HT TYPE="ITALIC">SECTION 3</HT></P></TI><STI><P><HT TYPE="BOLD"><HT TYPE="ITALIC">Planning and coordination of supervisory activities in preparation for and during emergency situations and final provisions</HT></HT></P></STI></TITLE><ARTICLE IDENTIFIER="032"><TI.ART>Article 32</TI.ART><STI.ART>Establishment of a college framework for emergency situations</STI.ART><PARAG IDENTIFIER="032.001"><NO.PARAG>1.</NO.PARAG><ALINEA>The competent authorities of the home Member State and the members of the college shall establish a college framework in anticipation of possible emergency situations in accordance with Article 112(1)(c) of Directive 2013/36/EU (hereinafter <QUOT.START CODE="2018" ID="QS0005" REF.END="QE0005"/>college framework for emergency situations<QUOT.END CODE="2019" ID="QE0005" REF.START="QS0005"/>).</ALINEA></PARAG><PARAG IDENTIFIER="032.002"><NO.PARAG>2.</NO.PARAG><ALINEA><P>The college framework for emergency situations shall include at least the following:</P><LIST TYPE="alpha"><ITEM><NP><NO.P>(a)</NO.P><TXT>the college-specific procedures that shall apply where an emergency situation as referred to in Article 114(1) of Directive 2013/36/EU arises;</TXT></NP></ITEM><ITEM><NP><NO.P>(b)</NO.P><TXT>the minimum set of information that shall be exchanged where an emergency situation as referred to in Article 114(1) of Directive 2013/36/EU arises.</TXT></NP></ITEM></LIST></ALINEA></PARAG><PARAG IDENTIFIER="032.003"><NO.PARAG>3.</NO.PARAG><ALINEA><P>The minimum set of information referred to in point (b) of paragraph 2 shall include the following:</P><LIST TYPE="alpha"><ITEM><NP><NO.P>(a)</NO.P><TXT>an outline of the situation that has occurred, including the underlying cause of the emergency situation, and the expected impact of the emergency situation on the institution, on the market liquidity and on the stability of the financial system;</TXT></NP></ITEM><ITEM><NP><NO.P>(b)</NO.P><TXT>an explanation of the measures and actions that have been taken or are planned to be taken, by the competent authorities of the home Member State or any of the members of the college or by the institution itself;</TXT></NP></ITEM><ITEM><NP><NO.P>(c)</NO.P><TXT>the latest available quantitative information regarding liquidity and capital position of the institution.</TXT></NP></ITEM></LIST></ALINEA></PARAG></ARTICLE><ARTICLE IDENTIFIER="033"><TI.ART>Article 33</TI.ART><STI.ART>General conditions with regard to exchange of information during an emergency situation</STI.ART><PARAG IDENTIFIER="033.001"><NO.PARAG>1.</NO.PARAG><ALINEA>The competent authorities of the home Member State and the members of the college shall exchange all information necessary to facilitate the exercise of the tasks referred to in Article 114(1) of Directive 2013/36/EU, subject to the confidentiality requirements laid down in Section II of Chapter 1 of Title VII of that Directive, and where applicable, Articles 54 and 58 of Directive 2004/39/EC.</ALINEA></PARAG><PARAG IDENTIFIER="033.002"><NO.PARAG>2.</NO.PARAG><ALINEA>Upon being alerted of an emergency situation by any member or observer of the college or having identified an emergency situation, the competent authorities of the home Member State shall communicate the information referred to in Article 32(2)(b), following the procedures referred to in Article 32(2)(a), to the members of the college who supervise branches that are affected or likely to be affected by the emergency situation, and the EBA.</ALINEA></PARAG><?PAGE NO="19"?><PARAG IDENTIFIER="033.003"><NO.PARAG>3.</NO.PARAG><ALINEA>Depending on the nature, severity, potential systemic impact or other impact, and likelihood of contagion of the emergency situation, the members of the college who supervise branches that are affected or likely to be affected by the emergency situation and the competent authorities of the home Member State may decide to exchange additional information.</ALINEA></PARAG><PARAG IDENTIFIER="033.004"><NO.PARAG>4.</NO.PARAG><ALINEA>The competent authorities of the home Member State shall consider whether the information referred to in paragraphs 2 and 3 is relevant for the performance of the tasks of the resolution college. In this case, the competent authorities of the home Member State shall communicate this information to the resolution authority as referred to in Article 3 of Directive 2014/59/EU.</ALINEA></PARAG><PARAG IDENTIFIER="033.005"><NO.PARAG>5.</NO.PARAG><ALINEA>The information referred to in paragraphs 2 and 3, where applicable, shall be updated immediately when new information is available.</ALINEA></PARAG><PARAG IDENTIFIER="033.006"><NO.PARAG>6.</NO.PARAG><ALINEA>When the exchange of information or communication referred to in this Article is made orally, the concerned competent authorities shall follow up it with written communication in a timely manner.</ALINEA></PARAG></ARTICLE><ARTICLE IDENTIFIER="034"><TI.ART>Article 34</TI.ART><STI.ART>Coordination of the supervisory assessment of an emergency situation</STI.ART><PARAG IDENTIFIER="034.001"><NO.PARAG>1.</NO.PARAG><ALINEA>Where an emergency situation occurs, the competent authorities of the home Member State shall coordinate the assessment of the emergency situation (hereinafter <QUOT.START CODE="2018" ID="QS0006" REF.END="QE0006"/>coordinated supervisory assessment<QUOT.END CODE="2019" ID="QE0006" REF.START="QS0006"/>) in cooperation with the members of the college pursuant to Article 112(3) of Directive 2013/36/EU.</ALINEA></PARAG><PARAG IDENTIFIER="034.002"><NO.PARAG>2.</NO.PARAG><ALINEA><P>The coordinated supervisory assessment of the emergency situation, prepared by the competent authorities of the home Member State, shall cover at least the following elements:</P><LIST TYPE="alpha"><ITEM><NP><NO.P>(a)</NO.P><TXT>the nature and severity of the emergency situation;</TXT></NP></ITEM><ITEM><NP><NO.P>(b)</NO.P><TXT>the impact or potential impact of the emergency situation on the institution and on any of its affected or likely to be affected branches;</TXT></NP></ITEM><ITEM><NP><NO.P>(c)</NO.P><TXT>the risk of cross-border contagion.</TXT></NP></ITEM></LIST></ALINEA></PARAG><PARAG IDENTIFIER="034.003"><NO.PARAG>3.</NO.PARAG><ALINEA>When assessing point (c) of paragraph 2, the competent authorities of the home Member State shall consider the potential systemic consequences in any of the Members States where significant branches are established.</ALINEA></PARAG></ARTICLE><ARTICLE IDENTIFIER="035"><TI.ART>Article 35</TI.ART><STI.ART>Coordination of the supervisory response to an emergency situation</STI.ART><PARAG IDENTIFIER="035.001"><NO.PARAG>1.</NO.PARAG><ALINEA>Where an emergency situation occurs, the competent authorities of the home Member State shall coordinate the development of a supervisory response to the emergency situation (hereinafter <QUOT.START CODE="2018" ID="QS0007" REF.END="QE0007"/>coordinated supervisory response<QUOT.END CODE="2019" ID="QE0007" REF.START="QS0007"/> in cooperation with the members of the college pursuant to Article 112(3) of Directive 2013/36/EU.</ALINEA></PARAG><PARAG IDENTIFIER="035.002"><NO.PARAG>2.</NO.PARAG><ALINEA>The coordinated supervisory assessment referred to in Article 34 shall form the basis of the coordinated supervisory response, which shall define the supervisory actions needed, their scope, and the timetable for their implementation.</ALINEA></PARAG></ARTICLE><ARTICLE IDENTIFIER="036"><TI.ART>Article 36</TI.ART><STI.ART>Monitoring of the implementation of the coordinated supervisory response to an emergency situation</STI.ART><PARAG IDENTIFIER="036.001"><NO.PARAG>1.</NO.PARAG><ALINEA>The competent authorities of the home Member State and the members of the college who supervise branches that are affected or likely to be affected by the emergency situation shall monitor and exchange information on the implementation of the coordinated supervisory response referred to in Article 35.</ALINEA></PARAG><?PAGE NO="20"?><PARAG IDENTIFIER="036.002"><NO.PARAG>2.</NO.PARAG><ALINEA>The information to be exchanged shall include at least an update on the implementation of the agreed actions within the foreseen timeline, as referred to in Article 35(2), and the need to update or adjust these actions.</ALINEA></PARAG></ARTICLE><ARTICLE IDENTIFIER="037"><TI.ART>Article 37</TI.ART><STI.ART>Coordination of external communication in an emergency situation</STI.ART><ALINEA>The competent authorities of the home Member State and the members of the college responsible for the supervision of branches affected or likely to be affected by an emergency situation shall coordinate to the extent possible their external communications, taking into account the elements specified under Article 22(2), as well as legal obligations or constraints under national law.</ALINEA></ARTICLE><ARTICLE IDENTIFIER="038"><TI.ART>Article 38</TI.ART><STI.ART>Entry into force</STI.ART><ALINEA>This Regulation shall enter into force on the twentieth day following that of its publication in the <HT TYPE="ITALIC">Official Journal of the European Union</HT>.</ALINEA></ARTICLE></DIVISION></DIVISION></ENACTING.TERMS><FINAL><P>This Regulation shall be binding in its entirety and directly applicable in all Member States.</P><SIGNATURE><PL.DATE><P>Done at Brussels, <DATE ISO="20151016">16 October 2015</DATE>.</P></PL.DATE><SIGNATORY><P><HT TYPE="ITALIC">For the Commission</HT></P><P><HT TYPE="ITALIC">The President</HT></P><P>Jean-Claude <HT TYPE="UC">Juncker</HT></P></SIGNATORY></SIGNATURE></FINAL></ACT>